{"1685577600": {"national": {"geographies": {"GB": {"variables": {"wholesale_price": 75.32818721115659, "post_balancing_price": 80.1124909604207, "load": 445424616.1425781, "single_rate_domestic": 0.0, "multi_rate_domestic": 0.0, "single_rate_nondomestic": 0.0, "multi_rate_nondomestic": 0.0}}}}, "eso": {"geographies": {"GB0 Z7": {"variables": {"wholesale_price": 76.49165950700448, "post_balancing_price": 77.83974821038004, "load": 26637422.64880371, "single_rate_domestic": 1.8104753099562845, "multi_rate_domestic": 1.9716624169467187, "single_rate_nondomestic": 1.8141938466435283, "multi_rate_nondomestic": 1.830116375895229}}, "GB0 Z6": {"variables": {"wholesale_price": 68.70848546283949, "post_balancing_price": 70.05657417673916, "load": 2576013.4069137573, "single_rate_domestic": 9.276074537542875, "multi_rate_domestic": 9.690596884756129, "single_rate_nondomestic": 8.931307070959232, "multi_rate_nondomestic": 9.083662196903294}}, "GB0 Z5": {"variables": {"wholesale_price": 68.70848546283949, "post_balancing_price": 70.05657417673916, "load": 11832574.282440186, "single_rate_domestic": 9.276074537542875, "multi_rate_domestic": 9.690596884756129, "single_rate_nondomestic": 8.931307070959232, "multi_rate_nondomestic": 9.083662196903294}}, "GB0 Z3": {"variables": {"wholesale_price": 45.2704944480428, "post_balancing_price": 46.61858318243505, "load": 728281.7206916809, "single_rate_domestic": 31.712978489078164, "multi_rate_domestic": 31.293110388282038, "single_rate_nondomestic": 30.968022226059848, "multi_rate_nondomestic": 30.644251120385203}}, "GB0 Z2": {"variables": {"wholesale_price": 44.869588665579386, "post_balancing_price": 46.21767739593466, "load": 1013350.911441803, "single_rate_domestic": 32.09580366762297, "multi_rate_domestic": 31.71335919918588, "single_rate_nondomestic": 31.31230486118488, "multi_rate_nondomestic": 31.006554858315212}}, "GB0 Z1_4": {"variables": {"wholesale_price": 45.02239911747757, "post_balancing_price": 46.37048784421768, "load": 450993.29414844513, "single_rate_domestic": 31.949884877267618, "multi_rate_domestic": 31.55317590534903, "single_rate_nondomestic": 31.181077063038956, "multi_rate_nondomestic": 30.868458079732804}}, "GB0 Z1_2": {"variables": {"wholesale_price": 0.0, "post_balancing_price": 0.0, "load": 0.0, "single_rate_domestic": 0.0, "multi_rate_domestic": 0.0, "single_rate_nondomestic": 0.0, "multi_rate_nondomestic": 0.0}}, "GB0 Z1_3": {"variables": {"wholesale_price": 45.01751480990992, "post_balancing_price": 46.36560353675631, "load": 194167.77165269852, "single_rate_domestic": 31.955029772111523, "multi_rate_domestic": 31.558485984310423, "single_rate_nondomestic": 31.184105623807902, "multi_rate_nondomestic": 30.872172492709726}}, "GB0 Z1_1": {"variables": {"wholesale_price": 0.0, "post_balancing_price": 0.0, "load": 0.0, "single_rate_domestic": 0.0, "multi_rate_domestic": 0.0, "single_rate_nondomestic": 0.0, "multi_rate_nondomestic": 0.0}}, "GB0 Z4": {"variables": {"wholesale_price": 0.0, "post_balancing_price": 0.0, "load": 0.0, "single_rate_domestic": 0.0, "multi_rate_domestic": 0.0, "single_rate_nondomestic": 0.0, "multi_rate_nondomestic": 0.0}}, "GB0 Z12": {"variables": {"wholesale_price": 76.56150938299352, "post_balancing_price": 77.90959809676035, "load": 32765829.333251953, "single_rate_domestic": 1.7377056811257114, "multi_rate_domestic": 1.8923366359621803, "single_rate_nondomestic": 1.772512403742646, "multi_rate_nondomestic": 1.7767820164571548}}, "GB0 Z14": {"variables": {"wholesale_price": 76.53345797913356, "post_balancing_price": 77.88154668030558, "load": 51571911.65905762, "single_rate_domestic": 1.7740442234942222, "multi_rate_domestic": 1.9226191231299923, "single_rate_nondomestic": 1.7994625607272734, "multi_rate_nondomestic": 1.8038262713039088}}, "GB0 Z15": {"variables": {"wholesale_price": 76.04637593740448, "post_balancing_price": 77.3944646316536, "load": 14238701.84954834, "single_rate_domestic": 2.266873129799331, "multi_rate_domestic": 2.295408747699067, "single_rate_nondomestic": 2.3166321745373613, "multi_rate_nondomestic": 2.2812031062394316}}, "GB0 Z17": {"variables": {"wholesale_price": 77.0594053984298, "post_balancing_price": 78.40749409707708, "load": 17735834.614135742, "single_rate_domestic": 1.1899047265384446, "multi_rate_domestic": 1.4626847811911252, "single_rate_nondomestic": 1.2592991278771142, "multi_rate_nondomestic": 1.291156237034319}}, "GB0 Z16": {"variables": {"wholesale_price": 77.23276069862291, "post_balancing_price": 78.5808493908618, "load": 26947623.56286621, "single_rate_domestic": 0.9991930911963081, "multi_rate_domestic": 1.3130000821430483, "single_rate_nondomestic": 1.0807545194093808, "multi_rate_nondomestic": 1.1221432960489965}}, "GB0 Z13": {"variables": {"wholesale_price": 76.9534797244009, "post_balancing_price": 78.3015684259132, "load": 50548957.21130371, "single_rate_domestic": 1.3064356692506898, "multi_rate_domestic": 1.554146946579992, "single_rate_nondomestic": 1.368395627782189, "multi_rate_nondomestic": 1.394428580379639}}, "GB0 Z11": {"variables": {"wholesale_price": 76.65833820049608, "post_balancing_price": 78.00642689925267, "load": 76409126.61694336, "single_rate_domestic": 1.6310935802178355, "multi_rate_domestic": 1.8091436899531905, "single_rate_nondomestic": 1.6721254551539435, "multi_rate_nondomestic": 1.682056793178504}}, "GB0 Z10": {"variables": {"wholesale_price": 76.6283821269377, "post_balancing_price": 77.97647083131172, "load": 13682645.220184326, "single_rate_domestic": 1.664244594385851, "multi_rate_domestic": 1.834095770767354, "single_rate_nondomestic": 1.704432305678662, "multi_rate_nondomestic": 1.7119720378444352}}, "GB0 Z9": {"variables": {"wholesale_price": 76.62760890153478, "post_balancing_price": 77.97569761200815, "load": 55987861.65270996, "single_rate_domestic": 1.6645776101524643, "multi_rate_domestic": 1.8371793854907115, "single_rate_nondomestic": 1.7013837268566583, "multi_rate_nondomestic": 1.7108496481705506}}, "GB0 Z8": {"variables": {"wholesale_price": 76.63941318212295, "post_balancing_price": 77.98750189393745, "load": 62103320.3996582, "single_rate_domestic": 1.6522246413533304, "multi_rate_domestic": 1.8240316369382388, "single_rate_nondomestic": 1.6939292978154565, "multi_rate_nondomestic": 1.701636103165231}}}}, "fti": {"geographies": {"GB1 - North Scotland": {"variables": {"wholesale_price": 44.91785123980671, "post_balancing_price": 46.11585414333444, "load": 2011295.603237152, "single_rate_domestic": 32.23330680613238, "multi_rate_domestic": 31.777423871120128, "single_rate_nondomestic": 31.416068018679987, "multi_rate_nondomestic": 31.10504405420204}}, "GB3 - South Scotland": {"variables": {"wholesale_price": 66.52971950629956, "post_balancing_price": 67.72772243279779, "load": 14784085.784545898, "single_rate_domestic": 11.538761099792778, "multi_rate_domestic": 11.998578632406035, "single_rate_nondomestic": 11.104655483275172, "multi_rate_nondomestic": 11.264272968756078}}, "GB4 - Upper North England": {"variables": {"wholesale_price": 75.69030557353388, "post_balancing_price": 76.88830847862096, "load": 36447056.900390625, "single_rate_domestic": 2.7146584850396906, "multi_rate_domestic": 3.0335542593764093, "single_rate_nondomestic": 2.6132186922351957, "multi_rate_nondomestic": 2.709591848517918}}, "GB5 - North England and North Wales": {"variables": {"wholesale_price": 76.72524956869539, "post_balancing_price": 77.92325247230183, "load": 110571464.20996094, "single_rate_domestic": 1.731143144767653, "multi_rate_domestic": 1.8782702701780118, "single_rate_nondomestic": 1.7792858814429242, "multi_rate_nondomestic": 1.7734838732791112}}, "GB6 - Midlands": {"variables": {"wholesale_price": 76.72524956869539, "post_balancing_price": 77.92325247230183, "load": 73049426.4946289, "single_rate_domestic": 1.7311431447676537, "multi_rate_domestic": 1.8782702701780127, "single_rate_nondomestic": 1.7792858814429249, "multi_rate_nondomestic": 1.7734838732791118}}, "GB7 - Central": {"variables": {"wholesale_price": 76.72524956869539, "post_balancing_price": 77.92325247230183, "load": 173799098.7080078, "single_rate_domestic": 1.7311431447676537, "multi_rate_domestic": 1.8782702701780127, "single_rate_nondomestic": 1.7792858814429249, "multi_rate_nondomestic": 1.7734838732791118}}, "GB8 - South Coast": {"variables": {"wholesale_price": 76.72524956869539, "post_balancing_price": 77.92325247230183, "load": 34762188.478759766, "single_rate_domestic": 1.7311431447676537, "multi_rate_domestic": 1.8782702701780127, "single_rate_nondomestic": 1.7792858814429249, "multi_rate_nondomestic": 1.7734838732791118}}}}, "nodal": {"geographies": {"4950": {"variables": {"wholesale_price": 76.55321089470566, "post_balancing_price": 76.55321089470566, "load": 1419439.4834976196, "single_rate_domestic": 3.009009265996341, "multi_rate_domestic": 3.231140626497093, "single_rate_nondomestic": 3.022367016067048, "multi_rate_nondomestic": 3.0373093716773476}}, "4951": {"variables": {"wholesale_price": 76.53588416358043, "post_balancing_price": 76.53588416358043, "load": 1285567.1546287537, "single_rate_domestic": 3.0253366252392238, "multi_rate_domestic": 3.2433434930434872, "single_rate_nondomestic": 3.0352157675790155, "multi_rate_nondomestic": 3.0493580724440523}}, "4952": {"variables": {"wholesale_price": 76.9267385967727, "post_balancing_price": 76.9267385967727, "load": 1276715.695777893, "single_rate_domestic": 2.6523095133523507, "multi_rate_domestic": 2.913454748028343, "single_rate_nondomestic": 2.7141397722771337, "multi_rate_nondomestic": 2.736753959739159}}, "4953": {"variables": {"wholesale_price": 76.84714543719447, "post_balancing_price": 76.84714543719447, "load": 1258785.003955841, "single_rate_domestic": 2.727994604768377, "multi_rate_domestic": 2.9802942414331226, "single_rate_nondomestic": 2.7778091136234635, "multi_rate_nondomestic": 2.7988564267446354}}, "4955": {"variables": {"wholesale_price": 76.70118501380578, "post_balancing_price": 76.70118501380578, "load": 2252543.897167206, "single_rate_domestic": 2.8674740041083275, "multi_rate_domestic": 3.104308832793084, "single_rate_nondomestic": 2.8986438296578254, "multi_rate_nondomestic": 2.916607540909076}}, "4956": {"variables": {"wholesale_price": 76.59857634167663, "post_balancing_price": 76.59857634167663, "load": 3542973.4192352295, "single_rate_domestic": 2.9655669993731975, "multi_rate_domestic": 3.1917085455328946, "single_rate_nondomestic": 2.984097082263885, "multi_rate_nondomestic": 2.999873306381198}}, "4958": {"variables": {"wholesale_price": 76.89405131646716, "post_balancing_price": 76.89405131646716, "load": 1898969.4271278381, "single_rate_domestic": 2.6834243529340904, "multi_rate_domestic": 2.940797508073114, "single_rate_nondomestic": 2.7406161391771677, "multi_rate_nondomestic": 2.762520594189299}}, "4960": {"variables": {"wholesale_price": 76.85031412273331, "post_balancing_price": 76.85031412273331, "load": 1106409.2609100342, "single_rate_domestic": 2.7252048457166387, "multi_rate_domestic": 2.9763115430542744, "single_rate_nondomestic": 2.77772542164771, "multi_rate_nondomestic": 2.798136873334359}}, "4961": {"variables": {"wholesale_price": 76.85968241104032, "post_balancing_price": 76.85968241104032, "load": 770020.8783092499, "single_rate_domestic": 2.7161380045093835, "multi_rate_domestic": 2.9691801158337507, "single_rate_nondomestic": 2.768821822951242, "multi_rate_nondomestic": 2.7898547993617906}}, "4962": {"variables": {"wholesale_price": 76.85536190959348, "post_balancing_price": 76.85536190959348, "load": 1960755.7685012817, "single_rate_domestic": 2.720192314088049, "multi_rate_domestic": 2.9719350405807456, "single_rate_nondomestic": 2.772948979833784, "multi_rate_nondomestic": 2.7936853814415445}}, "4963": {"variables": {"wholesale_price": 76.84877352234759, "post_balancing_price": 76.84877352234759, "load": 718452.3543148041, "single_rate_domestic": 2.7266764463929594, "multi_rate_domestic": 2.977467057623682, "single_rate_nondomestic": 2.7790616507259993, "multi_rate_nondomestic": 2.7993851053599315}}, "4964": {"variables": {"wholesale_price": 76.83425276841233, "post_balancing_price": 76.83425276841233, "load": 2542932.4675216675, "single_rate_domestic": 2.7406635298209627, "multi_rate_domestic": 2.9886177831942278, "single_rate_nondomestic": 2.7924072328324705, "multi_rate_nondomestic": 2.811871771767032}}, "4965": {"variables": {"wholesale_price": 76.83177693302042, "post_balancing_price": 76.83177693302042, "load": 1433519.9975624084, "single_rate_domestic": 2.7427074624914187, "multi_rate_domestic": 2.993917210950525, "single_rate_nondomestic": 2.790407820205235, "multi_rate_nondomestic": 2.8112977400152066}}, "4967": {"variables": {"wholesale_price": 76.85828478353416, "post_balancing_price": 76.85828478353416, "load": 2609299.265815735, "single_rate_domestic": 2.717382074260446, "multi_rate_domestic": 2.971509679245568, "single_rate_nondomestic": 2.7684378378863994, "multi_rate_nondomestic": 2.78992172892585}}, "4968": {"variables": {"wholesale_price": 76.79361241279224, "post_balancing_price": 76.79361241279224, "load": 2270385.1119651794, "single_rate_domestic": 2.77916956653682, "multi_rate_domestic": 3.0261783471975505, "single_rate_nondomestic": 2.8220389998523774, "multi_rate_nondomestic": 2.8420737523718493}}, "4969": {"variables": {"wholesale_price": 76.84756733429556, "post_balancing_price": 76.84756733429556, "load": 964105.8474502563, "single_rate_domestic": 2.7275066376014596, "multi_rate_domestic": 2.9769051703625635, "single_rate_nondomestic": 2.7803947469387875, "multi_rate_nondomestic": 2.8005960862161143}}, "4970": {"variables": {"wholesale_price": 76.78827953011456, "post_balancing_price": 76.78827953011456, "load": 810354.8609580994, "single_rate_domestic": 2.7855966942808505, "multi_rate_domestic": 3.0234266845244036, "single_rate_nondomestic": 2.839057144245049, "multi_rate_nondomestic": 2.8549437508049573}}, "4971": {"variables": {"wholesale_price": 76.79224799420759, "post_balancing_price": 76.79224799420759, "load": 2036785.2219696045, "single_rate_domestic": 2.7808862909596392, "multi_rate_domestic": 3.020577502221683, "single_rate_nondomestic": 2.829897181920876, "multi_rate_nondomestic": 2.8469952332286095}}, "4972": {"variables": {"wholesale_price": 76.7802532127706, "post_balancing_price": 76.7802532127706, "load": 1779644.4304733276, "single_rate_domestic": 2.7934634828541056, "multi_rate_domestic": 3.0295070068434304, "single_rate_nondomestic": 2.8473276058541463, "multi_rate_nondomestic": 2.8625687646862743}}, "4974": {"variables": {"wholesale_price": 76.788826341312, "post_balancing_price": 76.788826341312, "load": 561446.8149108887, "single_rate_domestic": 2.7849476471068004, "multi_rate_domestic": 3.0230340940865528, "single_rate_nondomestic": 2.83779498542752, "multi_rate_nondomestic": 2.853848521323715}}, "4975": {"variables": {"wholesale_price": 76.78924247456486, "post_balancing_price": 76.78924247456486, "load": 367791.72415447235, "single_rate_domestic": 2.7844537033321117, "multi_rate_domestic": 3.0227353281493756, "single_rate_nondomestic": 2.8368344629835427, "multi_rate_nondomestic": 2.853015030350882}}, "4977": {"variables": {"wholesale_price": 76.79072513227783, "post_balancing_price": 76.79072513227783, "load": 558667.0563430786, "single_rate_domestic": 2.7826938606694362, "multi_rate_domestic": 3.0216708495660036, "single_rate_nondomestic": 2.8334122305025318, "multi_rate_nondomestic": 2.850045405592357}}, "4979": {"variables": {"wholesale_price": 76.79113864004343, "post_balancing_price": 76.79113864004343, "load": 922730.9717178345, "single_rate_domestic": 2.782203026310329, "multi_rate_domestic": 3.0213739591154227, "single_rate_nondomestic": 2.832457739626993, "multi_rate_nondomestic": 2.8492171475520767}}, "5183": {"variables": {"wholesale_price": 76.79305886827487, "post_balancing_price": 76.79305886827487, "load": 1670518.8113555908, "single_rate_domestic": 2.7783384186612694, "multi_rate_domestic": 3.0175407446453493, "single_rate_nondomestic": 2.820389837922963, "multi_rate_nondomestic": 2.83835894336916}}, "5185": {"variables": {"wholesale_price": 76.7930611279934, "post_balancing_price": 76.7930611279934, "load": 5718244.488433838, "single_rate_domestic": 2.7783368227964775, "multi_rate_domestic": 3.01754077804231, "single_rate_nondomestic": 2.820389774828289, "multi_rate_nondomestic": 2.838359146282756}}, "5187": {"variables": {"wholesale_price": 76.79313876203283, "post_balancing_price": 76.79313876203283, "load": 1433196.8763160706, "single_rate_domestic": 2.778281417985334, "multi_rate_domestic": 3.0175419511499415, "single_rate_nondomestic": 2.8203876236352126, "multi_rate_nondomestic": 2.8383662402647123}}, "5188": {"variables": {"wholesale_price": 76.79283355323872, "post_balancing_price": 76.79283355323872, "load": 1549339.4812736511, "single_rate_domestic": 2.7784992001111304, "multi_rate_domestic": 3.0175373358925763, "single_rate_nondomestic": 2.8203960906497167, "multi_rate_nondomestic": 2.8383383621681313}}, "5189": {"variables": {"wholesale_price": 76.79331580867444, "post_balancing_price": 76.79331580867444, "load": 600137.6952667236, "single_rate_domestic": 2.778155106760974, "multi_rate_domestic": 3.0175446310305714, "single_rate_nondomestic": 2.8203827146971787, "multi_rate_nondomestic": 2.838382408176105}}, "5193": {"variables": {"wholesale_price": 76.7932170636511, "post_balancing_price": 76.7932170636511, "load": 3420353.7192230225, "single_rate_domestic": 2.7782255557309354, "multi_rate_domestic": 3.01754313798482, "single_rate_nondomestic": 2.8203854505439994, "multi_rate_nondomestic": 2.8383733895634906}}, "5194": {"variables": {"wholesale_price": 76.79434519675323, "post_balancing_price": 76.79434519675323, "load": 1073335.0885066986, "single_rate_domestic": 2.7776404414468217, "multi_rate_domestic": 3.017900505445113, "single_rate_nondomestic": 2.821412784396477, "multi_rate_nondomestic": 2.8394485812324506}}, "5195": {"variables": {"wholesale_price": 76.79316392086132, "post_balancing_price": 76.79316392086132, "load": 570306.5559511185, "single_rate_domestic": 2.7782634722931507, "multi_rate_domestic": 3.0175423300797, "single_rate_nondomestic": 2.8203869240198594, "multi_rate_nondomestic": 2.8383685389179787}}, "5198": {"variables": {"wholesale_price": 76.7933867672978, "post_balancing_price": 76.7933867672978, "load": 627722.2176628113, "single_rate_domestic": 2.7781044716698915, "multi_rate_domestic": 3.0175457063921147, "single_rate_nondomestic": 2.8203807473092564, "multi_rate_nondomestic": 2.838388886961125}}, "5200": {"variables": {"wholesale_price": 76.7934090548429, "post_balancing_price": 76.7934090548429, "load": 2167829.782661438, "single_rate_domestic": 2.7780885688456554, "multi_rate_domestic": 3.0175460378901384, "single_rate_nondomestic": 2.820380128791717, "multi_rate_nondomestic": 2.8383909217040233}}, "5202": {"variables": {"wholesale_price": 76.79420193236153, "post_balancing_price": 76.79420193236153, "load": 2413099.0192871094, "single_rate_domestic": 2.7776818283240616, "multi_rate_domestic": 3.017804148883772, "single_rate_nondomestic": 2.821123749230693, "multi_rate_nondomestic": 2.839166416745853}}, "5203": {"variables": {"wholesale_price": 76.79443408920501, "post_balancing_price": 76.79443408920501, "load": 1520371.4575195312, "single_rate_domestic": 2.7776147639176765, "multi_rate_domestic": 3.01796028350723, "single_rate_nondomestic": 2.8215920986584937, "multi_rate_nondomestic": 2.8396236346770807}}, "5204": {"variables": {"wholesale_price": 76.79431506284389, "post_balancing_price": 76.79431506284389, "load": 1001642.1805992126, "single_rate_domestic": 2.7776491463142103, "multi_rate_domestic": 3.0178802386257373, "single_rate_nondomestic": 2.8213519921207744, "multi_rate_nondomestic": 2.8393892344530682}}, "5206": {"variables": {"wholesale_price": 76.79453792644648, "post_balancing_price": 76.79453792644648, "load": 913965.0053596497, "single_rate_domestic": 2.7775847752094567, "multi_rate_domestic": 3.018030110965848, "single_rate_nondomestic": 2.82180154190514, "multi_rate_nondomestic": 2.8398281020349194}}, "5207": {"variables": {"wholesale_price": 76.79437952266836, "post_balancing_price": 76.79437952266836, "load": 2002457.768661499, "single_rate_domestic": 2.777630528886557, "multi_rate_domestic": 3.0179235844638925, "single_rate_nondomestic": 2.8214820044436655, "multi_rate_nondomestic": 2.8395161601738383}}, "5208": {"variables": {"wholesale_price": 76.79439801999864, "post_balancing_price": 76.79439801999864, "load": 1184022.381860733, "single_rate_domestic": 2.7776251846930395, "multi_rate_domestic": 3.0179360244381646, "single_rate_nondomestic": 2.8215193209178273, "multi_rate_nondomestic": 2.839552590338181}}, "5209": {"variables": {"wholesale_price": 76.79440641014267, "post_balancing_price": 76.79440641014267, "load": 1114441.4161338806, "single_rate_domestic": 2.7776227573772023, "multi_rate_domestic": 3.017941675967434, "single_rate_nondomestic": 2.821536278034437, "multi_rate_nondomestic": 2.839569143762519}}, "5212": {"variables": {"wholesale_price": 76.8304093364985, "post_balancing_price": 76.8304093364985, "load": 4696314.414611816, "single_rate_domestic": 2.73984873537336, "multi_rate_domestic": 2.9735631522376083, "single_rate_nondomestic": 2.777378653382621, "multi_rate_nondomestic": 2.79536265492375}}, "5213": {"variables": {"wholesale_price": 76.80615371303746, "post_balancing_price": 76.80615371303746, "load": 2561100.495651245, "single_rate_domestic": 2.7643382707802227, "multi_rate_domestic": 2.9995195988003114, "single_rate_nondomestic": 2.801533920790652, "multi_rate_nondomestic": 2.819620244840357}}, "5214": {"variables": {"wholesale_price": 76.81306188567932, "post_balancing_price": 76.81306188567932, "load": 2206774.7809181213, "single_rate_domestic": 2.7574823915226334, "multi_rate_domestic": 2.9925811540925427, "single_rate_nondomestic": 2.7949745937900627, "multi_rate_nondomestic": 2.8131078885671434}}, "5215": {"variables": {"wholesale_price": 76.79219722558801, "post_balancing_price": 76.79219722558801, "load": 2219154.0216827393, "single_rate_domestic": 2.7789532047870553, "multi_rate_domestic": 3.0175277090298356, "single_rate_nondomestic": 2.820413733974304, "multi_rate_nondomestic": 2.8382802532225093}}, "5217": {"variables": {"wholesale_price": 76.80607402034121, "post_balancing_price": 76.80607402034121, "load": 3311929.553337097, "single_rate_domestic": 2.764385363843232, "multi_rate_domestic": 2.9994696525957685, "single_rate_nondomestic": 2.801520283086594, "multi_rate_nondomestic": 2.819586237188346}}, "5218": {"variables": {"wholesale_price": 76.80901857500336, "post_balancing_price": 76.80901857500336, "load": 2004287.3778839111, "single_rate_domestic": 2.761478847417433, "multi_rate_domestic": 2.996577115741161, "single_rate_nondomestic": 2.798768751631708, "multi_rate_nondomestic": 2.816864402525929}}, "5219": {"variables": {"wholesale_price": 76.79867525161988, "post_balancing_price": 76.79867525161988, "load": 1807393.957359314, "single_rate_domestic": 2.771745926813661, "multi_rate_domestic": 3.0069706716763482, "single_rate_nondomestic": 2.808594113695698, "multi_rate_nondomestic": 2.8266209928269315}}, "5221": {"variables": {"wholesale_price": 76.80682808487498, "post_balancing_price": 76.80682808487498, "load": 3392208.7944488525, "single_rate_domestic": 2.763975925387905, "multi_rate_domestic": 3.0000185162185593, "single_rate_nondomestic": 2.8017218582756507, "multi_rate_nondomestic": 2.8200088654236053}}, "5222": {"variables": {"wholesale_price": 76.79645717071466, "post_balancing_price": 76.79645717071466, "load": 1583730.6412200928, "single_rate_domestic": 2.7741309125984133, "multi_rate_domestic": 3.009949439877036, "single_rate_nondomestic": 2.8112147689721714, "multi_rate_nondomestic": 2.82933999423096}}, "5223": {"variables": {"wholesale_price": 76.79341969610765, "post_balancing_price": 76.79341969610765, "load": 2011116.143245697, "single_rate_domestic": 2.7771480603708896, "multi_rate_domestic": 3.013029156969402, "single_rate_nondomestic": 2.814113574029521, "multi_rate_nondomestic": 2.8322183100614415}}, "5224": {"variables": {"wholesale_price": 76.79354056057886, "post_balancing_price": 76.79354056057886, "load": 1581808.1702346802, "single_rate_domestic": 2.777994752198345, "multi_rate_domestic": 3.017548030599824, "single_rate_nondomestic": 2.8203764806073353, "multi_rate_nondomestic": 2.838402927890087}}, "5225": {"variables": {"wholesale_price": 76.7936127572266, "post_balancing_price": 76.7936127572266, "load": 2390754.577194214, "single_rate_domestic": 2.777943215780602, "multi_rate_domestic": 3.017549119886186, "single_rate_nondomestic": 2.820374478639343, "multi_rate_nondomestic": 2.838409526726992}}, "5226": {"variables": {"wholesale_price": 76.79310809537613, "post_balancing_price": 76.79310809537613, "load": 2084869.5599861145, "single_rate_domestic": 2.7783033107825106, "multi_rate_domestic": 3.0175414898119883, "single_rate_nondomestic": 2.8203884745419536, "multi_rate_nondomestic": 2.838363438731465}}, "5228": {"variables": {"wholesale_price": 76.7938275833821, "post_balancing_price": 76.7938275833821, "load": 4622113.008811951, "single_rate_domestic": 2.777789966309926, "multi_rate_domestic": 3.017552369789476, "single_rate_nondomestic": 2.8203685241772725, "multi_rate_nondomestic": 2.8384291404059794}}, "5229": {"variables": {"wholesale_price": 76.79489609232216, "post_balancing_price": 76.79489609232216, "load": 3030404.3486099243, "single_rate_domestic": 2.77748130179552, "multi_rate_domestic": 3.0182710152937955, "single_rate_nondomestic": 2.8225241598323003, "multi_rate_nondomestic": 2.8405335427030387}}, "5230": {"variables": {"wholesale_price": 76.7951638943791, "post_balancing_price": 76.7951638943791, "load": 2363196.640083313, "single_rate_domestic": 2.7774039425528625, "multi_rate_domestic": 3.0184511300835153, "single_rate_nondomestic": 2.823064440530238, "multi_rate_nondomestic": 2.8410609824595885}}, "5231": {"variables": {"wholesale_price": 76.79515761154151, "post_balancing_price": 76.79515761154151, "load": 2034653.0237998962, "single_rate_domestic": 2.777405758048629, "multi_rate_domestic": 3.0184468976003798, "single_rate_nondomestic": 2.8230517442170315, "multi_rate_nondomestic": 2.841048590682769}}, "5233": {"variables": {"wholesale_price": 76.68316067440892, "post_balancing_price": 76.68316067440892, "load": 3085431.432411194, "single_rate_domestic": 2.8853814750154445, "multi_rate_domestic": 3.11918773972523, "single_rate_nondomestic": 2.9157214344512132, "multi_rate_nondomestic": 2.9328361906753804}}, "5234": {"variables": {"wholesale_price": 76.77598320262673, "post_balancing_price": 76.77598320262673, "load": 1267527.1502838135, "single_rate_domestic": 2.7953597937427617, "multi_rate_domestic": 3.0351500792566943, "single_rate_nondomestic": 2.836110288696407, "multi_rate_nondomestic": 2.8542804637395647}}, "5236": {"variables": {"wholesale_price": 76.75625247950951, "post_balancing_price": 76.75625247950951, "load": 1184298.5703868866, "single_rate_domestic": 2.8145825991784887, "multi_rate_domestic": 3.0537073012032097, "single_rate_nondomestic": 2.852985540239411, "multi_rate_nondomestic": 2.871124260868221}}, "5238": {"variables": {"wholesale_price": 76.78222185920265, "post_balancing_price": 76.78222185920265, "load": 719517.5922489166, "single_rate_domestic": 2.789845218848534, "multi_rate_domestic": 3.032186241330575, "single_rate_nondomestic": 2.8319126273985122, "multi_rate_nondomestic": 2.850676602954658}}, "5240": {"variables": {"wholesale_price": 76.69878555881238, "post_balancing_price": 76.69878555881238, "load": 2928207.0440979004, "single_rate_domestic": 2.8699693351828426, "multi_rate_domestic": 3.1048397824635865, "single_rate_nondomestic": 2.9016552606675594, "multi_rate_nondomestic": 2.9190088071084146}}, "5241": {"variables": {"wholesale_price": 76.80756480003745, "post_balancing_price": 76.80756480003745, "load": 815338.2213630676, "single_rate_domestic": 2.7657034209873306, "multi_rate_domestic": 3.0115078879261636, "single_rate_nondomestic": 2.8111074607065154, "multi_rate_nondomestic": 2.8306035466231485}}, "5242": {"variables": {"wholesale_price": 76.77710938293563, "post_balancing_price": 76.77710938293563, "load": 1853028.2019500732, "single_rate_domestic": 2.7951644203805013, "multi_rate_domestic": 3.038897686682179, "single_rate_nondomestic": 2.8372522355878242, "multi_rate_nondomestic": 2.856360565093018}}, "5243": {"variables": {"wholesale_price": 76.63295829193466, "post_balancing_price": 76.63295829193466, "load": 1464648.7268486023, "single_rate_domestic": 2.932892354588243, "multi_rate_domestic": 3.1611300825106246, "single_rate_nondomestic": 2.955996413700211, "multi_rate_nondomestic": 2.9720752840052347}}, "5245": {"variables": {"wholesale_price": 77.17106941763562, "post_balancing_price": 77.17106941763562, "load": 1589819.6690254211, "single_rate_domestic": 2.419588564161903, "multi_rate_domestic": 2.7094711098335313, "single_rate_nondomestic": 2.5152769673523645, "multi_rate_nondomestic": 2.5434662901591754}}, "5247": {"variables": {"wholesale_price": 77.07284976747904, "post_balancing_price": 77.07284976747904, "load": 3492370.276702881, "single_rate_domestic": 2.5131475588245484, "multi_rate_domestic": 2.7914535539392666, "single_rate_nondomestic": 2.595261669375129, "multi_rate_nondomestic": 2.621197707471868}}, "5248": {"variables": {"wholesale_price": 76.95126933423522, "post_balancing_price": 76.95126933423522, "load": 1371275.8031730652, "single_rate_domestic": 2.6289588041082403, "multi_rate_domestic": 2.8929348627352116, "single_rate_nondomestic": 2.6942700891292213, "multi_rate_nondomestic": 2.717416908807989}}, "5249": {"variables": {"wholesale_price": 76.78360840044455, "post_balancing_price": 76.78360840044455, "load": 2454284.2132492065, "single_rate_domestic": 2.7881343681468596, "multi_rate_domestic": 3.0287658309275707, "single_rate_nondomestic": 2.83020194609912, "multi_rate_nondomestic": 2.8484925714784466}}, "5250": {"variables": {"wholesale_price": 76.79716258330738, "post_balancing_price": 76.79716258330738, "load": 3066287.504119873, "single_rate_domestic": 2.775290798882184, "multi_rate_domestic": 3.017417496399776, "single_rate_nondomestic": 2.8196995629193813, "multi_rate_nondomestic": 2.838204290922683}}, "5251": {"variables": {"wholesale_price": 76.79633852540424, "post_balancing_price": 76.79633852540424, "load": 3085970.9980545044, "single_rate_domestic": 2.7761696108800757, "multi_rate_domestic": 3.0178553823801653, "single_rate_nondomestic": 2.821123347028028, "multi_rate_nondomestic": 2.839415581649753}}, "5252": {"variables": {"wholesale_price": 76.795159714368, "post_balancing_price": 76.795159714368, "load": 1367404.8729400635, "single_rate_domestic": 2.7774051558634607, "multi_rate_domestic": 3.0184483088313976, "single_rate_nondomestic": 2.8230559757759055, "multi_rate_nondomestic": 2.841052718582867}}, "5253": {"variables": {"wholesale_price": 76.79514290476227, "post_balancing_price": 76.79514290476227, "load": 898148.2315998077, "single_rate_domestic": 2.7774100117858334, "multi_rate_domestic": 3.0184369953977312, "single_rate_nondomestic": 2.8230220413655767, "multi_rate_nondomestic": 2.8410195877122226}}, "5254": {"variables": {"wholesale_price": 76.79518750880122, "post_balancing_price": 76.79518750880122, "load": 2606896.638442993, "single_rate_domestic": 2.7773971242297355, "multi_rate_domestic": 3.01846701219126, "single_rate_nondomestic": 2.8231120722809835, "multi_rate_nondomestic": 2.8411074837583454}}, "5256": {"variables": {"wholesale_price": 76.79949699072017, "post_balancing_price": 76.79949699072017, "load": 2805876.6970672607, "single_rate_domestic": 2.773389687884431, "multi_rate_domestic": 3.0178702281970016, "single_rate_nondomestic": 2.8178947316069314, "multi_rate_nondomestic": 2.837074631086817}}, "5257": {"variables": {"wholesale_price": 76.81660870069614, "post_balancing_price": 76.81660870069614, "load": 2822798.2852020264, "single_rate_domestic": 2.757091253529778, "multi_rate_domestic": 3.0033015676792827, "single_rate_nondomestic": 2.8042980843068035, "multi_rate_nondomestic": 2.823743689317949}}, "5258": {"variables": {"wholesale_price": 76.86012607310929, "post_balancing_price": 76.86012607310929, "load": 977408.6169338226, "single_rate_domestic": 2.7158024369969236, "multi_rate_domestic": 2.968247292755149, "single_rate_nondomestic": 2.7690941158231106, "multi_rate_nondomestic": 2.7898450713743768}}, "5259": {"variables": {"wholesale_price": 76.83376413560164, "post_balancing_price": 76.83376413560164, "load": 1299380.2227516174, "single_rate_domestic": 2.740814358909465, "multi_rate_domestic": 2.9894824596311724, "single_rate_nondomestic": 2.7904199578324107, "multi_rate_nondomestic": 2.810380161904059}}, "5261": {"variables": {"wholesale_price": 76.81333890202207, "post_balancing_price": 76.81333890202207, "load": 5618200.927307129, "single_rate_domestic": 2.7601466171329956, "multi_rate_domestic": 3.0053508021842603, "single_rate_nondomestic": 2.8071265358072686, "multi_rate_nondomestic": 2.826289627429611}}, "5262": {"variables": {"wholesale_price": 76.82553559894693, "post_balancing_price": 76.82553559894693, "load": 1999007.9878501892, "single_rate_domestic": 2.7487190042322713, "multi_rate_domestic": 2.995636092063612, "single_rate_nondomestic": 2.798100683971758, "multi_rate_nondomestic": 2.8175238025062206}}, "5264": {"variables": {"wholesale_price": 76.8792268906622, "post_balancing_price": 76.8792268906622, "load": 2560068.3443603516, "single_rate_domestic": 2.6976347998723034, "multi_rate_domestic": 2.9529232842585538, "single_rate_nondomestic": 2.7532844530651066, "multi_rate_nondomestic": 2.774680648482576}}, "5265": {"variables": {"wholesale_price": 76.84411742414973, "post_balancing_price": 76.84411742414973, "load": 1135903.5459899902, "single_rate_domestic": 2.7311239875219355, "multi_rate_domestic": 2.980959307732068, "single_rate_nondomestic": 2.7831000656232674, "multi_rate_nondomestic": 2.8031575779032445}}, "5266": {"variables": {"wholesale_price": 76.89139456665824, "post_balancing_price": 76.89139456665824, "load": 1849587.9865112305, "single_rate_domestic": 2.686006582290984, "multi_rate_domestic": 2.9428722013799966, "single_rate_nondomestic": 2.7431231141795687, "multi_rate_nondomestic": 2.764869726450333}}, "5268": {"variables": {"wholesale_price": 76.91265511667754, "post_balancing_price": 76.91265511667754, "load": 3458613.713745117, "single_rate_domestic": 2.6657277544656983, "multi_rate_domestic": 2.925201501696115, "single_rate_nondomestic": 2.7256289817043116, "multi_rate_nondomestic": 2.7479143127207357}}, "5269": {"variables": {"wholesale_price": 76.90131891245547, "post_balancing_price": 76.90131891245547, "load": 1279308.9554710388, "single_rate_domestic": 2.676522257795087, "multi_rate_domestic": 2.9346742306587177, "single_rate_nondomestic": 2.734835217928769, "multi_rate_nondomestic": 2.7568676448254035}}, "5270": {"variables": {"wholesale_price": 76.8462855179268, "post_balancing_price": 76.8462855179268, "load": 1512741.0609931946, "single_rate_domestic": 2.7290530254228558, "multi_rate_domestic": 2.9793331668742433, "single_rate_nondomestic": 2.7812196107390457, "multi_rate_nondomestic": 2.8014009586637694}}, "5272": {"variables": {"wholesale_price": 76.83472423989221, "post_balancing_price": 76.83472423989221, "load": 4198289.825576782, "single_rate_domestic": 2.7401097260998184, "multi_rate_domestic": 2.988317268237238, "single_rate_nondomestic": 2.791300826091363, "multi_rate_nondomestic": 2.810919842552832}}, "5273": {"variables": {"wholesale_price": 76.79351933031346, "post_balancing_price": 76.79351933031346, "load": 3870079.504234314, "single_rate_domestic": 2.7793772071404117, "multi_rate_domestic": 3.0196647082309993, "single_rate_nondomestic": 2.826962588910159, "multi_rate_nondomestic": 2.8444487546371913}}, "5274": {"variables": {"wholesale_price": 76.7946992171804, "post_balancing_price": 76.7946992171804, "load": 979113.8076934814, "single_rate_domestic": 2.7775381747910015, "multi_rate_domestic": 3.018138604916635, "single_rate_nondomestic": 2.82212698434703, "multi_rate_nondomestic": 2.840145807547006}}, "5888": {"variables": {"wholesale_price": 76.5716991128178, "post_balancing_price": 76.5716991128178, "load": 2188516.7325782776, "single_rate_domestic": 2.991587419239603, "multi_rate_domestic": 3.218119752117449, "single_rate_nondomestic": 3.0086569679209925, "multi_rate_nondomestic": 3.024453002610901}}, "5889": {"variables": {"wholesale_price": 76.58593450350743, "post_balancing_price": 76.58593450350743, "load": 1374513.878440857, "single_rate_domestic": 2.977805844017132, "multi_rate_domestic": 3.2041311987203756, "single_rate_nondomestic": 2.9956489558561614, "multi_rate_nondomestic": 3.011434496662803}}, "5896": {"variables": {"wholesale_price": 64.5838889346373, "post_balancing_price": 64.5838889346373, "load": 88013.61608242989, "single_rate_domestic": 14.651147144908832, "multi_rate_domestic": 14.86864346243103, "single_rate_nondomestic": 14.179267404329895, "multi_rate_nondomestic": 14.231372274889}}, "5898": {"variables": {"wholesale_price": 64.5828664415955, "post_balancing_price": 64.5828664415955, "load": 182760.14232730865, "single_rate_domestic": 14.65183612986963, "multi_rate_domestic": 14.86917851299385, "single_rate_nondomestic": 14.179801155657868, "multi_rate_nondomestic": 14.231931406431267}}, "5901": {"variables": {"wholesale_price": 64.58171342416627, "post_balancing_price": 64.58171342416627, "load": 427924.3783388138, "single_rate_domestic": 14.652613097196015, "multi_rate_domestic": 14.869781889908731, "single_rate_nondomestic": 14.18040306526723, "multi_rate_nondomestic": 14.232561930083907}}, "5902": {"variables": {"wholesale_price": 64.58465595071918, "post_balancing_price": 64.58465595071918, "load": 462859.06808662415, "single_rate_domestic": 14.650630276326508, "multi_rate_domestic": 14.868242054422547, "single_rate_nondomestic": 14.178866999705816, "multi_rate_nondomestic": 14.23095281968255}}, "5904": {"variables": {"wholesale_price": 64.58996789567638, "post_balancing_price": 64.58996789567638, "load": 792694.16913414, "single_rate_domestic": 14.647050872991366, "multi_rate_domestic": 14.865462334207635, "single_rate_nondomestic": 14.176094087862634, "multi_rate_nondomestic": 14.228048050974687}}, "5910": {"variables": {"wholesale_price": 64.59285227705557, "post_balancing_price": 64.59285227705557, "load": 513166.6283302307, "single_rate_domestic": 14.645108830629528, "multi_rate_domestic": 14.863953801533782, "single_rate_nondomestic": 14.17459066527807, "multi_rate_nondomestic": 14.226472486249518}}, "5912": {"variables": {"wholesale_price": 64.59745212517934, "post_balancing_price": 64.59745212517934, "load": 519266.7639827728, "single_rate_domestic": 14.642007658021694, "multi_rate_domestic": 14.86154583848426, "single_rate_nondomestic": 14.172187176664583, "multi_rate_nondomestic": 14.223955373903232}}, "5913": {"variables": {"wholesale_price": 64.92544769583444, "post_balancing_price": 64.92544769583444, "load": 244321.43456983566, "single_rate_domestic": 14.316711810984824, "multi_rate_domestic": 14.53735890309199, "single_rate_nondomestic": 13.85124650675681, "multi_rate_nondomestic": 13.908479723771832}}, "5914": {"variables": {"wholesale_price": 64.19092623366816, "post_balancing_price": 64.19092623366816, "load": 212989.65568304062, "single_rate_domestic": 15.05234392834012, "multi_rate_domestic": 15.273824993927805, "single_rate_nondomestic": 14.580244238408424, "multi_rate_nondomestic": 14.624306266892704}}, "5917": {"variables": {"wholesale_price": 63.79096823093699, "post_balancing_price": 63.79096823093699, "load": 910194.6517124176, "single_rate_domestic": 15.456050791852347, "multi_rate_domestic": 15.679443355340435, "single_rate_nondomestic": 14.981708700250602, "multi_rate_nondomestic": 15.018189069210045}}, "5919": {"variables": {"wholesale_price": 60.806081266844764, "post_balancing_price": 60.806081266844764, "load": 280789.88849544525, "single_rate_domestic": 18.393197136655658, "multi_rate_domestic": 18.583114681481305, "single_rate_nondomestic": 17.846478452218616, "multi_rate_nondomestic": 17.85607509673806}}, "5920": {"variables": {"wholesale_price": 71.31856524498257, "post_balancing_price": 71.31856524498257, "load": 528405.3756456375, "single_rate_domestic": 8.082004226706195, "multi_rate_domestic": 8.410720810010043, "single_rate_nondomestic": 7.814551645904491, "multi_rate_nondomestic": 7.905826744313348}}, "5922": {"variables": {"wholesale_price": 76.90407025431774, "post_balancing_price": 76.90407025431774, "load": 1462131.5905342102, "single_rate_domestic": 2.642336237384559, "multi_rate_domestic": 2.9094161844180477, "single_rate_nondomestic": 2.610709625060054, "multi_rate_nondomestic": 2.668157738206574}}, "5924": {"variables": {"wholesale_price": 77.30156888489626, "post_balancing_price": 77.30156888489626, "load": 189088.97287511826, "single_rate_domestic": 2.26703819669887, "multi_rate_domestic": 2.4832049000887424, "single_rate_nondomestic": 2.3170838921984163, "multi_rate_nondomestic": 2.334697399316456}}, "5926": {"variables": {"wholesale_price": 76.99246796548964, "post_balancing_price": 76.99246796548964, "load": 1043271.0148792267, "single_rate_domestic": 2.5765314407020448, "multi_rate_domestic": 2.8017837383247457, "single_rate_nondomestic": 2.617003233720559, "multi_rate_nondomestic": 2.634457834679628}}, "5927": {"variables": {"wholesale_price": 77.02777273357229, "post_balancing_price": 77.02777273357229, "load": 1407107.515777588, "single_rate_domestic": 2.5411491867995295, "multi_rate_domestic": 2.7652476844173512, "single_rate_nondomestic": 2.5826493381444617, "multi_rate_nondomestic": 2.6001031915397492}}, "5928": {"variables": {"wholesale_price": 77.06228991495327, "post_balancing_price": 77.06228991495327, "load": 642470.2116298676, "single_rate_domestic": 2.506556269122004, "multi_rate_domestic": 2.729526701313066, "single_rate_nondomestic": 2.5490618340857427, "multi_rate_nondomestic": 2.566514956635373}}, "5929": {"variables": {"wholesale_price": 76.92507873614319, "post_balancing_price": 76.92507873614319, "load": 1433215.2864608765, "single_rate_domestic": 2.6441048095839843, "multi_rate_domestic": 2.8716871889885947, "single_rate_nondomestic": 2.682685373786815, "multi_rate_nondomestic": 2.700162505582791}}, "5934": {"variables": {"wholesale_price": 76.92025617530653, "post_balancing_price": 76.92025617530653, "load": 1867853.9771347046, "single_rate_domestic": 2.6489811783773387, "multi_rate_domestic": 2.876873164505074, "single_rate_nondomestic": 2.6875065773542697, "multi_rate_nondomestic": 2.7050089343578314}}, "5939": {"variables": {"wholesale_price": 76.92913119428988, "post_balancing_price": 76.92913119428988, "load": 715292.6342449188, "single_rate_domestic": 2.640007184227132, "multi_rate_domestic": 2.867329400139235, "single_rate_nondomestic": 2.6786341039256194, "multi_rate_nondomestic": 2.6960900459582633}}, "5941": {"variables": {"wholesale_price": 76.96290332071494, "post_balancing_price": 76.96290332071494, "load": 2882153.0975723267, "single_rate_domestic": 2.606160959696541, "multi_rate_domestic": 2.8323794598281165, "single_rate_nondomestic": 2.645771589080449, "multi_rate_nondomestic": 2.6632268175951714}}, "5942": {"variables": {"wholesale_price": 76.9029148073938, "post_balancing_price": 76.9029148073938, "load": 1442634.047328949, "single_rate_domestic": 2.6665159408088694, "multi_rate_domestic": 2.895521241936751, "single_rate_nondomestic": 2.704842973374631, "multi_rate_nondomestic": 2.722436013218648}}, "5943": {"variables": {"wholesale_price": 67.1268043262176, "post_balancing_price": 67.1268043262176, "load": 643633.8353443146, "single_rate_domestic": 12.112503732388388, "multi_rate_domestic": 12.330872652067322, "single_rate_nondomestic": 11.6671297045761, "multi_rate_nondomestic": 11.763774685714344}}, "5944": {"variables": {"wholesale_price": 76.16618624538295, "post_balancing_price": 76.16618624538295, "load": 474277.2909898758, "single_rate_domestic": 3.393338324648159, "multi_rate_domestic": 3.6506692655378403, "single_rate_nondomestic": 3.3760297237299226, "multi_rate_nondomestic": 3.407785304414945}}, "5946": {"variables": {"wholesale_price": 75.70926439780766, "post_balancing_price": 75.70926439780766, "load": 2037093.0816383362, "single_rate_domestic": 3.8583833113409303, "multi_rate_domestic": 4.109677351538568, "single_rate_nondomestic": 3.849940887085663, "multi_rate_nondomestic": 3.865786814199097}}, "5949": {"variables": {"wholesale_price": 75.664816064706, "post_balancing_price": 75.664816064706, "load": 1378474.9081420898, "single_rate_domestic": 3.9039729232881553, "multi_rate_domestic": 4.154171573853339, "single_rate_nondomestic": 3.896076715987587, "multi_rate_nondomestic": 3.910308259041744}}, "5950": {"variables": {"wholesale_price": 75.71155152553085, "post_balancing_price": 75.71155152553085, "load": 1783725.5919036865, "single_rate_domestic": 3.857330529199249, "multi_rate_domestic": 4.106347268087997, "single_rate_nondomestic": 3.8502793356205207, "multi_rate_nondomestic": 3.8648311072198336}}, "5951": {"variables": {"wholesale_price": 75.75997135642811, "post_balancing_price": 75.75997135642811, "load": 1129472.4018535614, "single_rate_domestic": 3.8090071571625574, "multi_rate_domestic": 4.056799389831741, "single_rate_nondomestic": 3.8028314330533943, "multi_rate_nondomestic": 3.817714980462049}}, "5952": {"variables": {"wholesale_price": 77.59559201211154, "post_balancing_price": 77.59559201211154, "load": 864737.7551364899, "single_rate_domestic": 1.9730171495712525, "multi_rate_domestic": 2.181874979322726, "single_rate_nondomestic": 2.0329183005939484, "multi_rate_nondomestic": 2.0509000699033884}}, "5953": {"variables": {"wholesale_price": 75.80971245014894, "post_balancing_price": 75.80971245014894, "load": 805636.6744041443, "single_rate_domestic": 3.7593651028733377, "multi_rate_domestic": 4.005899407059292, "single_rate_nondomestic": 3.7540887380425056, "multi_rate_nondomestic": 3.769313113948456}}, "5954": {"variables": {"wholesale_price": 75.88577767195207, "post_balancing_price": 75.88577767195207, "load": 744897.2577400208, "single_rate_domestic": 3.680744089692949, "multi_rate_domestic": 3.928415656419195, "single_rate_nondomestic": 3.684077553413082, "multi_rate_nondomestic": 3.6982380416692777}}, "5955": {"variables": {"wholesale_price": 75.90075712334344, "post_balancing_price": 75.90075712334344, "load": 1315320.2265167236, "single_rate_domestic": 3.666660230227777, "multi_rate_domestic": 3.913244464979644, "single_rate_nondomestic": 3.666439140132083, "multi_rate_nondomestic": 3.681871098681841}}, "5957": {"variables": {"wholesale_price": 75.98216361200774, "post_balancing_price": 75.98216361200774, "load": 3729256.6426467896, "single_rate_domestic": 3.5851558120427898, "multi_rate_domestic": 3.829737837461091, "single_rate_nondomestic": 3.58842973867604, "multi_rate_nondomestic": 3.603685716635316}}, "5959": {"variables": {"wholesale_price": 75.94461558556155, "post_balancing_price": 75.94461558556155, "load": 1044012.9011516571, "single_rate_domestic": 3.6224302090630878, "multi_rate_domestic": 3.8681620996264705, "single_rate_nondomestic": 3.625694031805602, "multi_rate_nondomestic": 3.6405161562696136}}, "5960": {"variables": {"wholesale_price": 75.96810060115685, "post_balancing_price": 75.96810060115685, "load": 455225.5933017731, "single_rate_domestic": 3.5992721038342763, "multi_rate_domestic": 3.8440592739786896, "single_rate_nondomestic": 3.6024024002955994, "multi_rate_nondomestic": 3.617466072585104}}, "5961": {"variables": {"wholesale_price": 75.97715763481462, "post_balancing_price": 75.97715763481462, "load": 855184.1817684174, "single_rate_domestic": 3.5903411492076027, "multi_rate_domestic": 3.8347639862005343, "single_rate_nondomestic": 3.593419952416918, "multi_rate_nondomestic": 3.6085767820399024}}, "5962": {"variables": {"wholesale_price": 75.97907384683025, "post_balancing_price": 75.97907384683025, "load": 1628388.1543807983, "single_rate_domestic": 3.588356269313659, "multi_rate_domestic": 3.8328400387170585, "single_rate_nondomestic": 3.5915097622670484, "multi_rate_nondomestic": 3.606704543188439}}, "5963": {"variables": {"wholesale_price": 76.03022928298928, "post_balancing_price": 76.03022928298928, "load": 935343.4482860565, "single_rate_domestic": 3.5372173679638816, "multi_rate_domestic": 3.780403957945115, "single_rate_nondomestic": 3.5420830967535144, "multi_rate_nondomestic": 3.5573335781802258}}, "5966": {"variables": {"wholesale_price": 76.09900884281014, "post_balancing_price": 76.09900884281014, "load": 4646972.068763733, "single_rate_domestic": 3.468370253928435, "multi_rate_domestic": 3.70995469857033, "single_rate_nondomestic": 3.475551789909884, "multi_rate_nondomestic": 3.4909236516772926}}, "5967": {"variables": {"wholesale_price": 76.0757882435167, "post_balancing_price": 76.0757882435167, "load": 1385275.3610038757, "single_rate_domestic": 3.4916136463129317, "multi_rate_domestic": 3.73373898730275, "single_rate_nondomestic": 3.498013343823517, "multi_rate_nondomestic": 3.5133442297091704}}, "5968": {"variables": {"wholesale_price": 77.32804291512988, "post_balancing_price": 77.32804291512988, "load": 352193.3977651596, "single_rate_domestic": 2.240564369975748, "multi_rate_domestic": 2.456072974671117, "single_rate_nondomestic": 2.291497455458746, "multi_rate_nondomestic": 2.3091441223514675}}, "5969": {"variables": {"wholesale_price": 76.88148453974136, "post_balancing_price": 76.88148453974136, "load": 1501352.8753471375, "single_rate_domestic": 2.686705884644909, "multi_rate_domestic": 2.911835810171528, "single_rate_nondomestic": 2.721839413464284, "multi_rate_nondomestic": 2.738688066460654}}, "5971": {"variables": {"wholesale_price": 77.17167280358763, "post_balancing_price": 77.17167280358763, "load": 3394418.299964905, "single_rate_domestic": 2.396933364169211, "multi_rate_domestic": 2.616329044773805, "single_rate_nondomestic": 2.4426250358243964, "multi_rate_nondomestic": 2.460075846230749}}, "5973": {"variables": {"wholesale_price": 77.0401592415431, "post_balancing_price": 77.0401592415431, "load": 1431091.785709381, "single_rate_domestic": 2.5287355131323017, "multi_rate_domestic": 2.7524292040433513, "single_rate_nondomestic": 2.570596455430267, "multi_rate_nondomestic": 2.5880500472541788}}, "5974": {"variables": {"wholesale_price": 77.02183782495307, "post_balancing_price": 77.02183782495307, "load": 1581670.1361846924, "single_rate_domestic": 2.547097127563263, "multi_rate_domestic": 2.771389583662288, "single_rate_nondomestic": 2.5884244077794634, "multi_rate_nondomestic": 2.6058783865271016}}, "5976": {"variables": {"wholesale_price": 76.7932957280333, "post_balancing_price": 76.7932957280333, "load": 2635270.368270874, "single_rate_domestic": 2.774923524706769, "multi_rate_domestic": 3.0023540405908653, "single_rate_nondomestic": 2.8071673270901933, "multi_rate_nondomestic": 2.823922516683332}}, "5978": {"variables": {"wholesale_price": 76.8410752386987, "post_balancing_price": 76.8410752386987, "load": 2727514.2729797363, "single_rate_domestic": 2.7273330809731493, "multi_rate_domestic": 2.954255062092921, "single_rate_nondomestic": 2.761557302382792, "multi_rate_nondomestic": 2.7784807727702234}}, "5980": {"variables": {"wholesale_price": 76.86755959769792, "post_balancing_price": 76.86755959769792, "load": 3113924.3243103027, "single_rate_domestic": 2.7010716002524946, "multi_rate_domestic": 2.9281374023270788, "single_rate_nondomestic": 2.7366328773755777, "multi_rate_nondomestic": 2.7537174970142426}}, "5981": {"variables": {"wholesale_price": 76.86351764764696, "post_balancing_price": 76.86351764764696, "load": 1433080.4822425842, "single_rate_domestic": 2.705220795264059, "multi_rate_domestic": 2.9327738086092903, "single_rate_nondomestic": 2.7408625989857125, "multi_rate_nondomestic": 2.7580037343215507}}, "5982": {"variables": {"wholesale_price": 76.819645343553, "post_balancing_price": 76.819645343553, "load": 1280094.155303955, "single_rate_domestic": 2.748678205245458, "multi_rate_domestic": 2.9758282720735214, "single_rate_nondomestic": 2.78201417538602, "multi_rate_nondomestic": 2.798862168998868}}, "5983": {"variables": {"wholesale_price": 76.85205474664399, "post_balancing_price": 76.85205474664399, "load": 1560910.2135238647, "single_rate_domestic": 2.7165279582056816, "multi_rate_domestic": 2.9438057473211403, "single_rate_nondomestic": 2.751473575465641, "multi_rate_nondomestic": 2.768510953339633}}, "5984": {"variables": {"wholesale_price": 76.81720994956008, "post_balancing_price": 76.81720994956008, "load": 1401218.635772705, "single_rate_domestic": 2.7512637730757175, "multi_rate_domestic": 2.979017969782782, "single_rate_nondomestic": 2.7848258023858223, "multi_rate_nondomestic": 2.8017570156207183}}, "5986": {"variables": {"wholesale_price": 76.76950763741941, "post_balancing_price": 76.76950763741941, "load": 3688878.244377136, "single_rate_domestic": 2.7984197345857966, "multi_rate_domestic": 3.0253923192940975, "single_rate_nondomestic": 2.8292711749012196, "multi_rate_nondomestic": 2.84582847033832}}, "5987": {"variables": {"wholesale_price": 76.66582931161024, "post_balancing_price": 76.66582931161024, "load": 1291539.3176956177, "single_rate_domestic": 2.901788655125385, "multi_rate_domestic": 3.1302314009643646, "single_rate_nondomestic": 2.9285381606995906, "multi_rate_nondomestic": 2.9447875754280584}}, "5988": {"variables": {"wholesale_price": 76.73749642749696, "post_balancing_price": 76.73749642749696, "load": 1846042.8315200806, "single_rate_domestic": 2.830349129264912, "multi_rate_domestic": 3.0578248007214186, "single_rate_nondomestic": 2.859962666156279, "multi_rate_nondomestic": 2.876432847051836}}, "5989": {"variables": {"wholesale_price": 76.70745072024712, "post_balancing_price": 76.70745072024712, "load": 1232246.5300331116, "single_rate_domestic": 2.8603056737251973, "multi_rate_domestic": 3.088209247277958, "single_rate_nondomestic": 2.8887315566928344, "multi_rate_nondomestic": 2.9051128158748303}}, "5990": {"variables": {"wholesale_price": 76.7428575712513, "post_balancing_price": 76.7428575712513, "load": 1709021.6588478088, "single_rate_domestic": 2.825054141442318, "multi_rate_domestic": 3.0526337387331712, "single_rate_nondomestic": 2.8549844145917453, "multi_rate_nondomestic": 2.8714995964480163}}, "5992": {"variables": {"wholesale_price": 76.76299889022489, "post_balancing_price": 76.76299889022489, "load": 3387416.066581726, "single_rate_domestic": 2.8051331532766817, "multi_rate_domestic": 3.03300136233856, "single_rate_nondomestic": 2.836194170853308, "multi_rate_nondomestic": 2.852861950448494}}, "5993": {"variables": {"wholesale_price": 76.69080880646865, "post_balancing_price": 76.69080880646865, "load": 2096388.4387168884, "single_rate_domestic": 2.8767666044475635, "multi_rate_domestic": 3.104407341228066, "single_rate_nondomestic": 2.9043069597159286, "multi_rate_nondomestic": 2.920567489151259}}, "5995": {"variables": {"wholesale_price": 76.67399539650465, "post_balancing_price": 76.67399539650465, "load": 4596285.760871887, "single_rate_domestic": 2.8934028028109346, "multi_rate_domestic": 3.1208135499003604, "single_rate_nondomestic": 2.920034959628292, "multi_rate_nondomestic": 2.936174204755127}}, "5996": {"variables": {"wholesale_price": 76.66024862064721, "post_balancing_price": 76.66024862064721, "load": 2130757.670211792, "single_rate_domestic": 2.907004750028367, "multi_rate_domestic": 3.1342274596068287, "single_rate_nondomestic": 2.932894356818014, "multi_rate_nondomestic": 2.9489344381818228}}, "5997": {"variables": {"wholesale_price": 76.66469395434613, "post_balancing_price": 76.66469395434613, "load": 1997400.632534027, "single_rate_domestic": 2.9026062392389527, "multi_rate_domestic": 3.1298897531604792, "single_rate_nondomestic": 2.928735971530932, "multi_rate_nondomestic": 2.9448081190545574}}, "5998": {"variables": {"wholesale_price": 76.66069384999086, "post_balancing_price": 76.66069384999086, "load": 367818.70782756805, "single_rate_domestic": 2.9065641918076937, "multi_rate_domestic": 3.1337929902377493, "single_rate_nondomestic": 2.932477848250818, "multi_rate_nondomestic": 2.9485211406339014}}, "5999": {"variables": {"wholesale_price": 76.65655824893905, "post_balancing_price": 76.65655824893905, "load": 1832740.4883041382, "single_rate_domestic": 2.910656225088433, "multi_rate_domestic": 3.1378284542891444, "single_rate_nondomestic": 2.9363464881657078, "multi_rate_nondomestic": 2.952359952341423}}, "6001": {"variables": {"wholesale_price": 76.98376581440053, "post_balancing_price": 76.98376581440053, "load": 2295235.1236839294, "single_rate_domestic": 2.5852526554496094, "multi_rate_domestic": 2.8107893495116967, "single_rate_nondomestic": 2.6254709751774716, "multi_rate_nondomestic": 2.6429257590275337}}, "6003": {"variables": {"wholesale_price": 76.84680464378907, "post_balancing_price": 76.84680464378907, "load": 1754967.0687446594, "single_rate_domestic": 2.7232518795201215, "multi_rate_domestic": 2.955859430438465, "single_rate_nondomestic": 2.7609370716744963, "multi_rate_nondomestic": 2.7788235344337213}}, "6004": {"variables": {"wholesale_price": 76.8188869957345, "post_balancing_price": 76.8188869957345, "load": 1186729.7826843262, "single_rate_domestic": 2.7513679951273198, "multi_rate_domestic": 2.9854407500083555, "single_rate_nondomestic": 2.78853910255536, "multi_rate_nondomestic": 2.806500001088927}}, "6006": {"variables": {"wholesale_price": 76.82748095970327, "post_balancing_price": 76.82748095970327, "load": 3685824.8320236206, "single_rate_domestic": 2.741305299529643, "multi_rate_domestic": 2.9699407026156512, "single_rate_nondomestic": 2.7758427465215822, "multi_rate_nondomestic": 2.7929653183670644}}, "6007": {"variables": {"wholesale_price": 76.64934504995455, "post_balancing_price": 76.64934504995455, "load": 1610141.6753082275, "single_rate_domestic": 2.917793402481764, "multi_rate_domestic": 3.144866966898892, "single_rate_nondomestic": 2.9430940398991257, "multi_rate_nondomestic": 2.959055469755644}}, "6009": {"variables": {"wholesale_price": 76.64341268674993, "post_balancing_price": 76.64341268674993, "load": 4102450.101081848, "single_rate_domestic": 2.9236632595193917, "multi_rate_domestic": 3.1506556753463086, "single_rate_nondomestic": 2.9486434492881215, "multi_rate_nondomestic": 2.964562087075714}}, "6010": {"variables": {"wholesale_price": 76.63770689251835, "post_balancing_price": 76.63770689251835, "load": 2347433.3621292114, "single_rate_domestic": 2.929077269954073, "multi_rate_domestic": 3.155128846877595, "single_rate_nondomestic": 2.9533190247741166, "multi_rate_nondomestic": 2.969067745664993}}, "6012": {"variables": {"wholesale_price": 76.81135006105534, "post_balancing_price": 76.81135006105534, "load": 1616115.3916511536, "single_rate_domestic": 2.7588696004614737, "multi_rate_domestic": 2.9930801963361966, "single_rate_nondomestic": 2.7957485464518426, "multi_rate_nondomestic": 2.8136732518905787}}, "6013": {"variables": {"wholesale_price": 76.79852984410094, "post_balancing_price": 76.79852984410094, "load": 1551385.416545868, "single_rate_domestic": 2.771852995278974, "multi_rate_domestic": 3.0069655520780034, "single_rate_nondomestic": 2.808628313258556, "multi_rate_nondomestic": 2.8266311539500726}}, "6014": {"variables": {"wholesale_price": 76.78012159673689, "post_balancing_price": 76.78012159673689, "load": 1925523.47549057, "single_rate_domestic": 2.7903418771736996, "multi_rate_domestic": 3.0264411106695497, "single_rate_nondomestic": 2.8267582689931356, "multi_rate_nondomestic": 2.8447644527055056}}, "6016": {"variables": {"wholesale_price": 76.79802328378223, "post_balancing_price": 76.79802328378223, "load": 2584087.7302627563, "single_rate_domestic": 2.772226089223181, "multi_rate_domestic": 3.0069476949171308, "single_rate_nondomestic": 2.808747492274998, "multi_rate_nondomestic": 2.8266665553512564}}, "6018": {"variables": {"wholesale_price": 76.79889180393481, "post_balancing_price": 76.79889180393481, "load": 3709977.546180725, "single_rate_domestic": 2.7715864422311403, "multi_rate_domestic": 3.006978306197159, "single_rate_nondomestic": 2.808543173864634, "multi_rate_nondomestic": 2.826605858481244}}, "6019": {"variables": {"wholesale_price": 76.66582931161024, "post_balancing_price": 76.66582931161024, "load": 723528.3493824005, "single_rate_domestic": 2.901788655125385, "multi_rate_domestic": 3.1302314009643646, "single_rate_nondomestic": 2.9285381606995906, "multi_rate_nondomestic": 2.9447875754280584}}, "6020": {"variables": {"wholesale_price": 76.37316570386214, "post_balancing_price": 76.37316570386214, "load": 1516580.4488105774, "single_rate_domestic": 3.1941847262735488, "multi_rate_domestic": 3.4290025183680304, "single_rate_nondomestic": 3.2105604691687444, "multi_rate_nondomestic": 3.2262915593173083}}, "6021": {"variables": {"wholesale_price": 76.4420787668379, "post_balancing_price": 76.4420787668379, "load": 1870570.2637519836, "single_rate_domestic": 3.125277121402745, "multi_rate_domestic": 3.358373993897493, "single_rate_nondomestic": 3.1439620268363733, "multi_rate_nondomestic": 3.159776849670975}}, "6023": {"variables": {"wholesale_price": 76.6838803251902, "post_balancing_price": 76.6838803251902, "load": 674723.8736362457, "single_rate_domestic": 2.88380614579866, "multi_rate_domestic": 3.1120453973877824, "single_rate_nondomestic": 2.9113003323526714, "multi_rate_nondomestic": 2.927611829745682}}, "6025": {"variables": {"wholesale_price": 76.66582931161024, "post_balancing_price": 76.66582931161024, "load": 625011.5297431946, "single_rate_domestic": 2.901788655125385, "multi_rate_domestic": 3.1302314009643646, "single_rate_nondomestic": 2.9285381606995906, "multi_rate_nondomestic": 2.9447875754280584}}, "6026": {"variables": {"wholesale_price": 76.64765107237628, "post_balancing_price": 76.64765107237628, "load": 459433.942612648, "single_rate_domestic": 2.9199168995515716, "multi_rate_domestic": 3.1486327282689492, "single_rate_nondomestic": 2.945956110575157, "multi_rate_nondomestic": 2.962154013574223}}, "6028": {"variables": {"wholesale_price": 76.62662490932432, "post_balancing_price": 76.62662490932432, "load": 1517726.648475647, "single_rate_domestic": 2.9407226657137433, "multi_rate_domestic": 3.169156122855863, "single_rate_nondomestic": 2.96562912568177, "multi_rate_nondomestic": 2.981675976850251}}, "6029": {"variables": {"wholesale_price": 76.63576030158742, "post_balancing_price": 76.63576030158742, "load": 1299829.5299263, "single_rate_domestic": 2.9313228896728325, "multi_rate_domestic": 3.158538026564326, "single_rate_nondomestic": 2.956052984375688, "multi_rate_nondomestic": 2.9719652770727603}}, "6030": {"variables": {"wholesale_price": 76.63743851796481, "post_balancing_price": 76.63743851796481, "load": 558561.0740804672, "single_rate_domestic": 2.929643083021969, "multi_rate_domestic": 3.1568093783917015, "single_rate_nondomestic": 2.954428023858358, "multi_rate_nondomestic": 2.970341706165933}}, "6031": {"variables": {"wholesale_price": 76.63893441810258, "post_balancing_price": 76.63893441810258, "load": 2277216.646068573, "single_rate_domestic": 2.9280672027175982, "multi_rate_domestic": 3.1548975157612467, "single_rate_nondomestic": 2.9527552058142983, "multi_rate_nondomestic": 2.9686264885957088}}, "6032": {"variables": {"wholesale_price": 76.56685555142958, "post_balancing_price": 76.56685555142958, "load": 542375.9222297668, "single_rate_domestic": 3.000556599467792, "multi_rate_domestic": 3.230737372399899, "single_rate_nondomestic": 3.0235539612566886, "multi_rate_nondomestic": 3.039559040301657}}, "6033": {"variables": {"wholesale_price": 76.5966434174956, "post_balancing_price": 76.5966434174956, "load": 1319797.4978523254, "single_rate_domestic": 2.970158141742835, "multi_rate_domestic": 3.197076790232761, "single_rate_nondomestic": 2.99263813716064, "multi_rate_nondomestic": 3.0082519078878667}}, "6035": {"variables": {"wholesale_price": 76.51030988270905, "post_balancing_price": 76.51030988270905, "load": 4421272.451705933, "single_rate_domestic": 3.056978327791598, "multi_rate_domestic": 3.288150579178766, "single_rate_nondomestic": 3.0777902238006036, "multi_rate_nondomestic": 3.093648690370669}}, "6036": {"variables": {"wholesale_price": 76.51030988270905, "post_balancing_price": 76.51030988270905, "load": 2229194.172580719, "single_rate_domestic": 3.056978327791598, "multi_rate_domestic": 3.288150579178766, "single_rate_nondomestic": 3.0777902238006036, "multi_rate_nondomestic": 3.093648690370669}}, "6037": {"variables": {"wholesale_price": 76.51030988270905, "post_balancing_price": 76.51030988270905, "load": 1789793.4183006287, "single_rate_domestic": 3.056978327791598, "multi_rate_domestic": 3.288150579178766, "single_rate_nondomestic": 3.0777902238006036, "multi_rate_nondomestic": 3.093648690370669}}, "6038": {"variables": {"wholesale_price": 76.57064336878476, "post_balancing_price": 76.57064336878476, "load": 1411616.044330597, "single_rate_domestic": 2.9965849732979217, "multi_rate_domestic": 3.2260553696639436, "single_rate_nondomestic": 3.0192776641283134, "multi_rate_nondomestic": 3.0351747199566557}}, "6039": {"variables": {"wholesale_price": 76.5645085374351, "post_balancing_price": 76.5645085374351, "load": 1285420.8962936401, "single_rate_domestic": 3.002725906897425, "multi_rate_domestic": 3.232369349761297, "single_rate_nondomestic": 3.025227351677418, "multi_rate_nondomestic": 3.0411204864196986}}, "6040": {"variables": {"wholesale_price": 76.51030988270905, "post_balancing_price": 76.51030988270905, "load": 519818.1976413727, "single_rate_domestic": 3.056978327791598, "multi_rate_domestic": 3.288150579178766, "single_rate_nondomestic": 3.0777902238006036, "multi_rate_nondomestic": 3.093648690370669}}, "6041": {"variables": {"wholesale_price": 76.56274849953189, "post_balancing_price": 76.56274849953189, "load": 1133725.7457809448, "single_rate_domestic": 3.004487687135142, "multi_rate_domestic": 3.2341807778701903, "single_rate_nondomestic": 3.0269342681220683, "multi_rate_nondomestic": 3.0428262764079435}}, "6042": {"variables": {"wholesale_price": 76.5669995079145, "post_balancing_price": 76.5669995079145, "load": 1330943.270565033, "single_rate_domestic": 3.000232467496017, "multi_rate_domestic": 3.229805650222674, "single_rate_nondomestic": 3.0228115671870843, "multi_rate_nondomestic": 3.0387062937399323}}, "6043": {"variables": {"wholesale_price": 76.56647411814245, "post_balancing_price": 76.56647411814245, "load": 808374.132850647, "single_rate_domestic": 3.000758374970519, "multi_rate_domestic": 3.2303463805240753, "single_rate_nondomestic": 3.023321096766033, "multi_rate_nondomestic": 3.0392154898934107}}, "6045": {"variables": {"wholesale_price": 76.61833237840345, "post_balancing_price": 76.61833237840345, "load": 2982766.2247161865, "single_rate_domestic": 2.947460981859723, "multi_rate_domestic": 3.170317863073468, "single_rate_nondomestic": 2.969195308538394, "multi_rate_nondomestic": 2.984367075002263}}, "6046": {"variables": {"wholesale_price": 76.62005837052843, "post_balancing_price": 76.62005837052843, "load": 970118.8684864044, "single_rate_domestic": 2.9474322543510545, "multi_rate_domestic": 3.17723251522662, "single_rate_nondomestic": 2.9724786641265917, "multi_rate_nondomestic": 2.9886694410884855}}, "6047": {"variables": {"wholesale_price": 76.61434490087127, "post_balancing_price": 76.61434490087127, "load": 2310098.128665924, "single_rate_domestic": 2.9488176349010518, "multi_rate_domestic": 3.16224788671889, "single_rate_nondomestic": 2.965941888929085, "multi_rate_nondomestic": 2.979742833980517}}, "6048": {"variables": {"wholesale_price": 76.6634778743017, "post_balancing_price": 76.6634778743017, "load": 1152456.6376018524, "single_rate_domestic": 2.904953624923518, "multi_rate_domestic": 3.137180733287196, "single_rate_nondomestic": 2.933481721741239, "multi_rate_nondomestic": 2.9502626372253387}}, "6050": {"variables": {"wholesale_price": 76.76062605262965, "post_balancing_price": 76.76062605262965, "load": 4382804.035598755, "single_rate_domestic": 2.8100303433165434, "multi_rate_domestic": 3.047505704819237, "single_rate_nondomestic": 2.8462599053936692, "multi_rate_nondomestic": 2.86433606281296}}, "6051": {"variables": {"wholesale_price": 76.75901956828555, "post_balancing_price": 76.75901956828555, "load": 2498002.298187256, "single_rate_domestic": 2.8117024481310913, "multi_rate_domestic": 3.0497836348794447, "single_rate_nondomestic": 2.848730322755984, "multi_rate_nondomestic": 2.866829463908357}}, "6437": {"variables": {"wholesale_price": 44.44973433403999, "post_balancing_price": 44.44973433403999, "load": 78460.01702594757, "single_rate_domestic": 33.71675069974319, "multi_rate_domestic": 33.555501848762134, "single_rate_nondomestic": 32.90132414963259, "multi_rate_nondomestic": 32.675660528413346}}, "6439": {"variables": {"wholesale_price": 44.44984871122755, "post_balancing_price": 44.44984871122755, "load": 101174.30510520935, "single_rate_domestic": 33.716607743806556, "multi_rate_domestic": 33.5554056768946, "single_rate_nondomestic": 32.901169434956046, "multi_rate_nondomestic": 32.67552610247872}}, "6440": {"variables": {"wholesale_price": 44.44989506476947, "post_balancing_price": 44.44989506476947, "load": 190328.85828447342, "single_rate_domestic": 33.71654980102444, "multi_rate_domestic": 33.55536669749312, "single_rate_nondomestic": 32.90110673078598, "multi_rate_nondomestic": 32.67547161164835}}, "6441": {"variables": {"wholesale_price": 44.44974770540755, "post_balancing_price": 44.44974770540755, "load": 31070.73155003786, "single_rate_domestic": 33.71670469418839, "multi_rate_domestic": 33.5554818220606, "single_rate_nondomestic": 32.901249340479666, "multi_rate_nondomestic": 32.6756090583846}}, "6442": {"variables": {"wholesale_price": 44.44974770540755, "post_balancing_price": 44.44974770540755, "load": 121243.2450606823, "single_rate_domestic": 33.71670469418839, "multi_rate_domestic": 33.5554818220606, "single_rate_nondomestic": 32.901249340479666, "multi_rate_nondomestic": 32.6756090583846}}, "6443": {"variables": {"wholesale_price": 44.44974770540755, "post_balancing_price": 44.44974770540755, "load": 41853.79501414299, "single_rate_domestic": 33.71670469418839, "multi_rate_domestic": 33.5554818220606, "single_rate_nondomestic": 32.901249340479666, "multi_rate_nondomestic": 32.6756090583846}}, "6447": {"variables": {"wholesale_price": 44.45030936572542, "post_balancing_price": 44.45030936572542, "load": 90839.48811769485, "single_rate_domestic": 33.71603197866337, "multi_rate_domestic": 33.55501834045691, "single_rate_nondomestic": 32.90054631679526, "multi_rate_nondomestic": 32.67498468441255}}, "6448": {"variables": {"wholesale_price": 44.45028591808238, "post_balancing_price": 44.45028591808238, "load": 247463.7214331627, "single_rate_domestic": 33.71606129193706, "multi_rate_domestic": 33.555038057720225, "single_rate_nondomestic": 32.90057804080815, "multi_rate_nondomestic": 32.675012246254575}}, "6451": {"variables": {"wholesale_price": 44.44962646909704, "post_balancing_price": 44.44962646909704, "load": 81030.11378836632, "single_rate_domestic": 33.716885510143285, "multi_rate_domestic": 33.555592544898666, "single_rate_nondomestic": 32.901470053004125, "multi_rate_nondomestic": 32.67578730179401}}, "6453": {"variables": {"wholesale_price": 64.5632759357923, "post_balancing_price": 64.5632759357923, "load": 163176.50861358643, "single_rate_domestic": 14.665037111905797, "multi_rate_domestic": 14.87943021919148, "single_rate_nondomestic": 14.19002776370885, "multi_rate_nondomestic": 14.242644273409715}}, "6454": {"variables": {"wholesale_price": 64.5632759357923, "post_balancing_price": 64.5632759357923, "load": 13406.574486225843, "single_rate_domestic": 14.665037111905797, "multi_rate_domestic": 14.87943021919148, "single_rate_nondomestic": 14.19002776370885, "multi_rate_nondomestic": 14.242644273409715}}, "6455": {"variables": {"wholesale_price": 64.57024795063232, "post_balancing_price": 64.57024795063232, "load": 93474.10034632683, "single_rate_domestic": 14.660339068323593, "multi_rate_domestic": 14.875781779165187, "single_rate_nondomestic": 14.18638823789455, "multi_rate_nondomestic": 14.238831711383105}}, "6457": {"variables": {"wholesale_price": 64.5632759357923, "post_balancing_price": 64.5632759357923, "load": 176406.85437631607, "single_rate_domestic": 14.665037111905797, "multi_rate_domestic": 14.87943021919148, "single_rate_nondomestic": 14.19002776370885, "multi_rate_nondomestic": 14.242644273409715}}, "6458": {"variables": {"wholesale_price": 64.5550789442434, "post_balancing_price": 64.5550789442434, "load": 560113.8137865067, "single_rate_domestic": 14.670560615208919, "multi_rate_domestic": 14.883719710052356, "single_rate_nondomestic": 14.194306736155827, "multi_rate_nondomestic": 14.247126728405739}}, "6460": {"variables": {"wholesale_price": 50.566065488538044, "post_balancing_price": 50.566065488538044, "load": 91443.14724946022, "single_rate_domestic": 27.998920130348615, "multi_rate_domestic": 27.663448314581295, "single_rate_nondomestic": 27.187956169977063, "multi_rate_nondomestic": 26.9855599794204}}, "6462": {"variables": {"wholesale_price": 40.61586050704201, "post_balancing_price": 40.61586050704201, "load": 141613.73923420906, "single_rate_domestic": 37.35103338263629, "multi_rate_domestic": 37.11867032216904, "single_rate_nondomestic": 36.467780353373776, "multi_rate_nondomestic": 36.18963863162365}}, "6464": {"variables": {"wholesale_price": 64.5341183067117, "post_balancing_price": 64.5341183067117, "load": 276660.6194219589, "single_rate_domestic": 14.68466935858416, "multi_rate_domestic": 14.89467985338082, "single_rate_nondomestic": 14.205226258279577, "multi_rate_nondomestic": 14.258571956725506}}, "6466": {"variables": {"wholesale_price": 64.57945521781134, "post_balancing_price": 64.57945521781134, "load": 292308.27719306946, "single_rate_domestic": 14.654140944661316, "multi_rate_domestic": 14.870967008587566, "single_rate_nondomestic": 14.181590803061939, "multi_rate_nondomestic": 14.23380353721812}}, "6467": {"variables": {"wholesale_price": 64.58389703181798, "post_balancing_price": 64.58389703181798, "load": 303478.1536245346, "single_rate_domestic": 14.651146322730627, "multi_rate_domestic": 14.868641766065277, "single_rate_nondomestic": 14.17926988370978, "multi_rate_nondomestic": 14.231372910645634}}, "6468": {"variables": {"wholesale_price": 66.05468147605693, "post_balancing_price": 66.05468147605693, "load": 189810.38252830505, "single_rate_domestic": 13.234616446191463, "multi_rate_domestic": 13.476623391133566, "single_rate_nondomestic": 12.800637185404899, "multi_rate_nondomestic": 12.8717534753191}}, "6469": {"variables": {"wholesale_price": 66.03262998521987, "post_balancing_price": 66.03262998521987, "load": 338332.94622612, "single_rate_domestic": 13.249480693800642, "multi_rate_domestic": 13.488165665417606, "single_rate_nondomestic": 12.812155629355697, "multi_rate_nondomestic": 12.883817530959302}}, "6471": {"variables": {"wholesale_price": 64.5319963998777, "post_balancing_price": 64.5319963998777, "load": 352530.2197380066, "single_rate_domestic": 14.686116743216838, "multi_rate_domestic": 14.895799936899811, "single_rate_nondomestic": 14.20635924396732, "multi_rate_nondomestic": 14.259751451640598}}, "6472": {"variables": {"wholesale_price": 64.52942186304053, "post_balancing_price": 64.52942186304053, "load": 207501.70065307617, "single_rate_domestic": 14.687872879471866, "multi_rate_domestic": 14.897158908341872, "single_rate_nondomestic": 14.20773387648853, "multi_rate_nondomestic": 14.26118252836531}}, "6474": {"variables": {"wholesale_price": 55.9518699766804, "post_balancing_price": 55.9518699766804, "load": 168648.93909549713, "single_rate_domestic": 22.772970920097002, "multi_rate_domestic": 22.885549630967514, "single_rate_nondomestic": 22.368645375728935, "multi_rate_nondomestic": 22.26376475008958}}, "6475": {"variables": {"wholesale_price": 58.48788837614527, "post_balancing_price": 58.48788837614527, "load": 175801.30712080002, "single_rate_domestic": 20.382550229593285, "multi_rate_domestic": 20.52372121180177, "single_rate_nondomestic": 19.9558098728716, "multi_rate_nondomestic": 19.897740491535398}}, "6477": {"variables": {"wholesale_price": 65.96324862581119, "post_balancing_price": 65.96324862581119, "load": 438229.2569513321, "single_rate_domestic": 13.296248575574555, "multi_rate_domestic": 13.524481484732929, "single_rate_nondomestic": 12.848396470257356, "multi_rate_nondomestic": 12.921775064854822}}, "6480": {"variables": {"wholesale_price": 65.95147169110463, "post_balancing_price": 65.95147169110463, "load": 410087.32890987396, "single_rate_domestic": 13.30418706877874, "multi_rate_domestic": 13.530645823371593, "single_rate_nondomestic": 12.85454804664884, "multi_rate_nondomestic": 12.928218049671802}}, "6482": {"variables": {"wholesale_price": 65.9227306889838, "post_balancing_price": 65.9227306889838, "load": 1268637.3775901794, "single_rate_domestic": 13.328177856807335, "multi_rate_domestic": 13.552447195001479, "single_rate_nondomestic": 12.87619022108074, "multi_rate_nondomestic": 12.94996959044271}}, "6484": {"variables": {"wholesale_price": 65.98769497293853, "post_balancing_price": 65.98769497293853, "load": 400665.05339336395, "single_rate_domestic": 13.26258141350969, "multi_rate_domestic": 13.486529527183592, "single_rate_nondomestic": 12.810947902271439, "multi_rate_nondomestic": 12.88596176620678}}, "6485": {"variables": {"wholesale_price": 44.450413540798934, "post_balancing_price": 44.450413540798934, "load": 76310.17815446854, "single_rate_domestic": 33.715901775300466, "multi_rate_domestic": 33.55493074775716, "single_rate_nondomestic": 32.90040540498376, "multi_rate_nondomestic": 32.67486224725567}}, "6486": {"variables": {"wholesale_price": 44.450435671338006, "post_balancing_price": 44.450435671338006, "load": 121324.37583184242, "single_rate_domestic": 33.71587412072981, "multi_rate_domestic": 33.554912145016786, "single_rate_nondomestic": 32.9003754763814, "multi_rate_nondomestic": 32.67483624257902}}, "7286": {"variables": {"wholesale_price": 76.99929823331719, "post_balancing_price": 76.99929823331719, "load": 2855469.7835464478, "single_rate_domestic": 2.5832089627071824, "multi_rate_domestic": 2.8528458918185584, "single_rate_nondomestic": 2.655158007693247, "multi_rate_nondomestic": 2.679406671396397}}, "7361": {"variables": {"wholesale_price": 76.77824768597715, "post_balancing_price": 76.77824768597715, "load": 2842945.1953125, "single_rate_domestic": 2.793214028751287, "multi_rate_domestic": 3.0332541235320094, "single_rate_nondomestic": 2.8343556661585056, "multi_rate_nondomestic": 2.852561610600444}}, "7412": {"variables": {"wholesale_price": 76.91722079825011, "post_balancing_price": 76.91722079825011, "load": 1463770.647556305, "single_rate_domestic": 2.6520503985345014, "multi_rate_domestic": 2.8801372524533364, "single_rate_nondomestic": 2.6905410728761026, "multi_rate_nondomestic": 2.708059299909829}}, "7454": {"variables": {"wholesale_price": 76.63014115864503, "post_balancing_price": 76.63014115864503, "load": 2901347.8672561646, "single_rate_domestic": 2.9360676747810808, "multi_rate_domestic": 3.164646636324444, "single_rate_nondomestic": 2.959595916876328, "multi_rate_nondomestic": 2.975699227471728}}, "7455": {"variables": {"wholesale_price": 76.83186451579154, "post_balancing_price": 76.83186451579154, "load": 2125442.310436249, "single_rate_domestic": 2.738379841522536, "multi_rate_domestic": 2.972007942821791, "single_rate_nondomestic": 2.77593067875038, "multi_rate_nondomestic": 2.793908695279193}}, "7456": {"variables": {"wholesale_price": 76.825972331589, "post_balancing_price": 76.825972331589, "load": 1492828.8662452698, "single_rate_domestic": 2.74428455662454, "multi_rate_domestic": 2.978136964273076, "single_rate_nondomestic": 2.781676308407317, "multi_rate_nondomestic": 2.7996514110901805}}, "7457": {"variables": {"wholesale_price": 76.83555750435936, "post_balancing_price": 76.83555750435936, "load": 1492828.8662452698, "single_rate_domestic": 2.7346082023033795, "multi_rate_domestic": 2.96789057431231, "single_rate_nondomestic": 2.7721366131235228, "multi_rate_nondomestic": 2.790071561816863}}, "7458": {"variables": {"wholesale_price": 76.7933290393343, "post_balancing_price": 76.7933290393343, "load": 1512368.2526855469, "single_rate_domestic": 2.7781456655709476, "multi_rate_domestic": 3.0175448280412946, "single_rate_nondomestic": 2.8203823483520214, "multi_rate_nondomestic": 2.83838361230184}}, "7461": {"variables": {"wholesale_price": 76.79837452846427, "post_balancing_price": 76.79837452846427, "load": 1657345.781402588, "single_rate_domestic": 2.7722263588631835, "multi_rate_domestic": 3.00800538722479, "single_rate_nondomestic": 2.809384905912542, "multi_rate_nondomestic": 2.8275230737493677}}, "7462": {"variables": {"wholesale_price": 76.80268807893633, "post_balancing_price": 76.80268807893633, "load": 1657345.781402588, "single_rate_domestic": 2.7679459954925436, "multi_rate_domestic": 3.0036491308568443, "single_rate_nondomestic": 2.8052802344342664, "multi_rate_nondomestic": 2.8234502256337946}}, "7463": {"variables": {"wholesale_price": 76.80988476192181, "post_balancing_price": 76.80988476192181, "load": 1888602.3787384033, "single_rate_domestic": 2.760741475926424, "multi_rate_domestic": 2.9961778126665317, "single_rate_nondomestic": 2.798277092670815, "multi_rate_nondomestic": 2.8164565694873813}}, "7464": {"variables": {"wholesale_price": 76.81144422065135, "post_balancing_price": 76.81144422065135, "load": 1888602.3787384033, "single_rate_domestic": 2.7592566049316707, "multi_rate_domestic": 2.994854021870009, "single_rate_nondomestic": 2.7969665708121836, "multi_rate_nondomestic": 2.8151966051112365}}, "7465": {"variables": {"wholesale_price": 76.81666177948615, "post_balancing_price": 76.81666177948615, "load": 2386604.780357361, "single_rate_domestic": 2.753789651360596, "multi_rate_domestic": 2.9885059143670873, "single_rate_nondomestic": 2.7912326597233923, "multi_rate_nondomestic": 2.8093136293548726}}, "7466": {"variables": {"wholesale_price": 76.82189447589421, "post_balancing_price": 76.82189447589421, "load": 2386604.780357361, "single_rate_domestic": 2.7485727670545246, "multi_rate_domestic": 2.983162369898031, "single_rate_nondomestic": 2.786201299100977, "multi_rate_nondomestic": 2.8043023615136686}}, "7469": {"variables": {"wholesale_price": 64.97034229603109, "post_balancing_price": 64.97034229603109, "load": 221193.05460643768, "single_rate_domestic": 14.272186702361255, "multi_rate_domestic": 14.492985571810394, "single_rate_nondomestic": 13.807317524759172, "multi_rate_nondomestic": 13.865298770464152}}, "7471": {"variables": {"wholesale_price": 65.99299553345536, "post_balancing_price": 65.99299553345536, "load": 181423.44935035706, "single_rate_domestic": 13.25693978762417, "multi_rate_domestic": 13.48072746610161, "single_rate_nondomestic": 12.80520897606892, "multi_rate_nondomestic": 12.880361310043257}}, "7908": {"variables": {"wholesale_price": 76.8541267070584, "post_balancing_price": 76.8541267070584, "load": 3043349.1624298096, "single_rate_domestic": 2.715848182892203, "multi_rate_domestic": 2.9479856622236995, "single_rate_nondomestic": 2.7536171332314607, "multi_rate_nondomestic": 2.771465306518153}}, "7909": {"variables": {"wholesale_price": 76.58575013221915, "post_balancing_price": 76.58575013221915, "load": 2493009.7325286865, "single_rate_domestic": 2.9801319897124343, "multi_rate_domestic": 3.2016074490431654, "single_rate_nondomestic": 2.9987727355987563, "multi_rate_nondomestic": 3.013354177818035}}, "7945": {"variables": {"wholesale_price": 76.79299583330858, "post_balancing_price": 76.79299583330858, "load": 569892.6093101501, "single_rate_domestic": 2.7783834083137506, "multi_rate_domestic": 3.0175397884654935, "single_rate_nondomestic": 2.820391590063253, "multi_rate_nondomestic": 2.838353183398492}}, "7946": {"variables": {"wholesale_price": 76.58123601963855, "post_balancing_price": 76.58123601963855, "load": 868054.5397415161, "single_rate_domestic": 2.9860800410761867, "multi_rate_domestic": 3.215571606649793, "single_rate_nondomestic": 3.009345916653442, "multi_rate_nondomestic": 3.025311435118304}}, "8013": {"variables": {"wholesale_price": 44.45039918364389, "post_balancing_price": 44.45039918364389, "load": 116027.11800050735, "single_rate_domestic": 33.71591972382966, "multi_rate_domestic": 33.55494282060358, "single_rate_nondomestic": 32.900424830112804, "multi_rate_nondomestic": 32.67487912322956}}, "8014": {"variables": {"wholesale_price": 76.83374512408032, "post_balancing_price": 76.83374512408032, "load": 1550040.4375839233, "single_rate_domestic": 2.7412598265841117, "multi_rate_domestic": 2.988941351002363, "single_rate_nondomestic": 2.793598533980063, "multi_rate_nondomestic": 2.8128967387535693}}, "8015": {"variables": {"wholesale_price": 44.45042867966955, "post_balancing_price": 44.45042867966955, "load": 269942.8823747635, "single_rate_domestic": 33.71588285251668, "multi_rate_domestic": 33.55491802003393, "single_rate_nondomestic": 32.90038492673813, "multi_rate_nondomestic": 32.674844452391504}}, "8016": {"variables": {"wholesale_price": 76.79441725229617, "post_balancing_price": 76.79441725229617, "load": 2502982.132835388, "single_rate_domestic": 2.7776196233956, "multi_rate_domestic": 3.017948973113375, "single_rate_nondomestic": 2.8215581754146606, "multi_rate_nondomestic": 2.8395905192134183}}, "8017": {"variables": {"wholesale_price": 75.56038562172363, "post_balancing_price": 75.56038562172363, "load": 826735.2730026245, "single_rate_domestic": 4.008877674219885, "multi_rate_domestic": 4.26048594540878, "single_rate_nondomestic": 3.9998421889611167, "multi_rate_nondomestic": 4.0126314833537995}}, "8019": {"variables": {"wholesale_price": 40.325435200605455, "post_balancing_price": 40.325435200605455, "load": 34586.80395466089, "single_rate_domestic": 37.57252491645642, "multi_rate_domestic": 37.528495526670675, "single_rate_nondomestic": 36.754150875606186, "multi_rate_nondomestic": 36.51269440233936}}, "8020": {"variables": {"wholesale_price": 53.87449889049581, "post_balancing_price": 53.87449889049581, "load": 375498.09430122375, "single_rate_domestic": 24.74767271068804, "multi_rate_domestic": 24.81352660033175, "single_rate_nondomestic": 24.278473057196607, "multi_rate_nondomestic": 24.150122953419153}}, "8021": {"variables": {"wholesale_price": 76.5592474069462, "post_balancing_price": 76.5592474069462, "load": 1649534.522342682, "single_rate_domestic": 3.0079922354249464, "multi_rate_domestic": 3.2377840837879934, "single_rate_nondomestic": 3.030329675760218, "multi_rate_nondomestic": 3.046219445331795}}, "8022": {"variables": {"wholesale_price": 77.10475622729561, "post_balancing_price": 77.10475622729561, "load": 1968994.4378356934, "single_rate_domestic": 2.4639967720939753, "multi_rate_domestic": 2.6855793631248255, "single_rate_nondomestic": 2.5077392957227063, "multi_rate_nondomestic": 2.525191522585209}}, "8023": {"variables": {"wholesale_price": 76.92742304495788, "post_balancing_price": 76.92742304495788, "load": 1431326.1635627747, "single_rate_domestic": 2.641734380895215, "multi_rate_domestic": 2.869166256576964, "single_rate_nondomestic": 2.6803417605044264, "multi_rate_nondomestic": 2.6978066331053805}}, "8024": {"variables": {"wholesale_price": 76.8320577787869, "post_balancing_price": 76.8320577787869, "load": 1798699.074584961, "single_rate_domestic": 2.7423687539909816, "multi_rate_domestic": 2.992192512995195, "single_rate_nondomestic": 2.790502047803714, "multi_rate_nondomestic": 2.8109580560746026}}, "8025": {"variables": {"wholesale_price": 77.11671607942205, "post_balancing_price": 77.11671607942205, "load": 1798699.074584961, "single_rate_domestic": 2.4713627550325095, "multi_rate_domestic": 2.754839008153963, "single_rate_nondomestic": 2.5595393472465546, "multi_rate_nondomestic": 2.5864817233460324}}, "8026": {"variables": {"wholesale_price": 77.22534483323541, "post_balancing_price": 77.22534483323541, "load": 2039149.457168579, "single_rate_domestic": 2.34326172520549, "multi_rate_domestic": 2.5613232140382114, "single_rate_nondomestic": 2.3907524442039527, "multi_rate_nondomestic": 2.408270477998126}}, "8027": {"variables": {"wholesale_price": 77.34808612646044, "post_balancing_price": 77.34808612646044, "load": 1001051.9190597534, "single_rate_domestic": 2.220521299664033, "multi_rate_domestic": 2.4355316689268216, "single_rate_nondomestic": 2.2721262217819045, "multi_rate_nondomestic": 2.289797990485756}}, "8029": {"variables": {"wholesale_price": 76.63660414796739, "post_balancing_price": 76.63660414796739, "load": 1740869.348564148, "single_rate_domestic": 2.930358867594493, "multi_rate_domestic": 3.157104821078192, "single_rate_nondomestic": 2.9548948279249476, "multi_rate_nondomestic": 2.970741467045617}}, "8030": {"variables": {"wholesale_price": 76.81298027089761, "post_balancing_price": 76.81298027089761, "load": 2739848.991531372, "single_rate_domestic": 2.760547224469759, "multi_rate_domestic": 3.0063907522831093, "single_rate_nondomestic": 2.8071811556648223, "multi_rate_nondomestic": 2.8265704224687402}}, "8032": {"variables": {"wholesale_price": 66.03830687329592, "post_balancing_price": 66.03830687329592, "load": 176665.40152311325, "single_rate_domestic": 13.245654053830222, "multi_rate_domestic": 13.485194238758769, "single_rate_nondomestic": 12.809190321002715, "multi_rate_nondomestic": 12.880711771574394}}, "8033": {"variables": {"wholesale_price": 65.94365354768946, "post_balancing_price": 65.94365354768946, "load": 437656.3322715759, "single_rate_domestic": 13.309457039996838, "multi_rate_domestic": 13.53473803050798, "single_rate_nondomestic": 12.85863180616864, "multi_rate_nondomestic": 12.932495252200413}}, "8034": {"variables": {"wholesale_price": 65.85372866676549, "post_balancing_price": 65.85372866676549, "load": 227829.347635746, "single_rate_domestic": 13.396071385566769, "multi_rate_domestic": 13.619856874328569, "single_rate_nondomestic": 12.942931955432238, "multi_rate_nondomestic": 13.01563208264725}}, "8035": {"variables": {"wholesale_price": 64.58629890106623, "post_balancing_price": 64.58629890106623, "load": 459373.18724155426, "single_rate_domestic": 14.64952702909874, "multi_rate_domestic": 14.86738442869714, "single_rate_nondomestic": 14.178014881668334, "multi_rate_nondomestic": 14.230058587493499}}, "8036": {"variables": {"wholesale_price": 64.58376528109103, "post_balancing_price": 64.58376528109103, "load": 220398.26732254028, "single_rate_domestic": 14.65123046630035, "multi_rate_domestic": 14.868708164495093, "single_rate_nondomestic": 14.179331965295138, "multi_rate_nondomestic": 14.231439896048867}}, "8037": {"variables": {"wholesale_price": 64.5876320176291, "post_balancing_price": 64.5876320176291, "load": 380074.3692436218, "single_rate_domestic": 14.648624890608463, "multi_rate_domestic": 14.866684707040916, "single_rate_nondomestic": 14.177313468066629, "multi_rate_nondomestic": 14.2293254060131}}, "8093": {"variables": {"wholesale_price": 76.83208020472236, "post_balancing_price": 76.83208020472236, "load": 1798699.074584961, "single_rate_domestic": 2.7423473943790455, "multi_rate_domestic": 2.99217482720674, "single_rate_nondomestic": 2.7904831825809295, "multi_rate_nondomestic": 2.8109400698311586}}, "8189": {"variables": {"wholesale_price": 76.79297318829711, "post_balancing_price": 76.79297318829711, "load": 949279.4054985046, "single_rate_domestic": 2.7783995723095747, "multi_rate_domestic": 3.0175394461690788, "single_rate_nondomestic": 2.8203922159640173, "multi_rate_nondomestic": 2.838351115065869}}, "8283": {"variables": {"wholesale_price": 76.58268226075738, "post_balancing_price": 76.58268226075738, "load": 4764496.258674622, "single_rate_domestic": 2.982940908358438, "multi_rate_domestic": 3.20288341170589, "single_rate_nondomestic": 3.000500416145445, "multi_rate_nondomestic": 3.014791122473677}}, "8290": {"variables": {"wholesale_price": 76.79299149694667, "post_balancing_price": 76.79299149694667, "load": 1408303.4052848816, "single_rate_domestic": 2.7783865144022704, "multi_rate_domestic": 3.017539725097454, "single_rate_nondomestic": 2.820391708586747, "multi_rate_nondomestic": 2.8383527893242317}}, "8397": {"variables": {"wholesale_price": 76.79335180416041, "post_balancing_price": 76.79335180416041, "load": 1430218.0357627869, "single_rate_domestic": 2.7781294230785223, "multi_rate_domestic": 3.0175451755124856, "single_rate_nondomestic": 2.820381716026185, "multi_rate_nondomestic": 2.838385692078662}}, "8473": {"variables": {"wholesale_price": 76.736459244123, "post_balancing_price": 76.736459244123, "load": 2517050.0144958496, "single_rate_domestic": 2.833659340977247, "multi_rate_domestic": 3.071318757940606, "single_rate_nondomestic": 2.8697487553937937, "multi_rate_nondomestic": 2.8876170404817945}}, "8489": {"variables": {"wholesale_price": 66.02803793281784, "post_balancing_price": 66.02803793281784, "load": 183558.70965909958, "single_rate_domestic": 13.252576042588089, "multi_rate_domestic": 13.490569243881474, "single_rate_nondomestic": 12.814554241604181, "multi_rate_nondomestic": 12.886329756630797}}, "8515": {"variables": {"wholesale_price": 76.79305301545823, "post_balancing_price": 76.79305301545823, "load": 2799826.9496307373, "single_rate_domestic": 2.778342624726207, "multi_rate_domestic": 3.0175406557516475, "single_rate_nondomestic": 2.8203900049412898, "multi_rate_nondomestic": 2.8383584068457224}}, "8529": {"variables": {"wholesale_price": 76.79305653065542, "post_balancing_price": 76.79305653065542, "load": 2824242.596885681, "single_rate_domestic": 2.778340086968251, "multi_rate_domestic": 3.017540709790914, "single_rate_nondomestic": 2.8203899046677985, "multi_rate_nondomestic": 2.8383587325774964}}, "8565": {"variables": {"wholesale_price": 64.85822309393721, "post_balancing_price": 64.85822309393721, "load": 289775.90313100815, "single_rate_domestic": 14.383383052927268, "multi_rate_domestic": 14.603802868819054, "single_rate_nondomestic": 13.917025143291179, "multi_rate_nondomestic": 13.973138267374521}}, "8575": {"variables": {"wholesale_price": 76.83016452884935, "post_balancing_price": 76.83016452884935, "load": 2670396.5930023193, "single_rate_domestic": 2.7387238675551946, "multi_rate_domestic": 2.96766472201761, "single_rate_nondomestic": 2.7735578033668133, "multi_rate_nondomestic": 2.790742001989232}}, "8578": {"variables": {"wholesale_price": 76.75691503453513, "post_balancing_price": 76.75691503453513, "load": 4409491.606712341, "single_rate_domestic": 2.813892975163051, "multi_rate_domestic": 3.052767818560456, "single_rate_nondomestic": 2.851966668947535, "multi_rate_nondomestic": 2.8700959164849187}}, "8649": {"variables": {"wholesale_price": 76.79980596211661, "post_balancing_price": 76.79980596211661, "load": 1800101.4686660767, "single_rate_domestic": 2.7705724381792347, "multi_rate_domestic": 3.005626966716482, "single_rate_nondomestic": 2.8073774416811563, "multi_rate_nondomestic": 2.825380176737611}}, "8744": {"variables": {"wholesale_price": 64.58560281262346, "post_balancing_price": 64.58560281262346, "load": 170933.7299771309, "single_rate_domestic": 14.649992271607445, "multi_rate_domestic": 14.86774658429551, "single_rate_nondomestic": 14.178372739829037, "multi_rate_nondomestic": 14.230435056390414}}, "8747": {"variables": {"wholesale_price": 76.79196899279894, "post_balancing_price": 76.79196899279894, "load": 1833720.4263000488, "single_rate_domestic": 2.7791160224672784, "multi_rate_domestic": 3.0175242605895143, "single_rate_nondomestic": 2.8204200615570874, "multi_rate_nondomestic": 2.8382594155123555}}, "8838": {"variables": {"wholesale_price": 76.83642050275513, "post_balancing_price": 76.83642050275513, "load": 1144132.9500236511, "single_rate_domestic": 2.7323998373801492, "multi_rate_domestic": 2.96093448865752, "single_rate_nondomestic": 2.767304341214166, "multi_rate_nondomestic": 2.7844576929797853}}, "8860": {"variables": {"wholesale_price": 76.45943423876612, "post_balancing_price": 76.45943423876612, "load": 3424557.6760787964, "single_rate_domestic": 3.098158869763687, "multi_rate_domestic": 3.3071550634193807, "single_rate_nondomestic": 3.09747237838689, "multi_rate_nondomestic": 3.1098608271292725}}}}, "last_update": "1715765400"}}